Workbook

Sheet Leia-me
A1: BDRs da B3 — levantamento BRAPI
A3: Fonte | B3: BRAPI (brapi.dev) — /api/v2/tickers?subType=bdr e /api/v2/stocks/quote (1 ativo por chamada)
A4: Plano | B4: Gratuito (token do PrimeVest) — 892 requisições da cota mensal
A5: Coletado em | B5: 24/09/2026 (madrugada), com a cotação do fechamento de 23/09/2026
A6: Horário da cotação | B6: 23/09/2026 18:31 (Brasília) — regularMarketTime 21:31:30 UTC, igual para todos
A7: Universo | B7: 892 BDRs: 657 de ação (sufixo 34), 223 de ETF (39), 6 com sufixo 31, 2 com 32, 2 com 33, 1 com 35 (Alphabet classe C) e 1 unit (PPLA11). Todos marcados ativos pela BRAPI
A8: Filtro | B8: Nenhum BDR excluído: diferente dos ETFs, a lista não trouxe duplicatas nem ativos de outro tipo. Casos estranhos estão na coluna "Observação"
A9: Catálogo PrimeVest | B9: O tipo BDR existe (price_source BRAPI), mas o catálogo não tem nenhum BDR cadastrado
A10: Setor | B10: A BRAPI dá o setor em inglês (padrão internacional); a coluna "Setor (pt-BR)" é tradução nossa. Subsetor vem vazio em 891 de 892
A11: Proporção | B11: "Ações por BDR" vem do texto "Repr X Sh" do nome longo da BRAPI; 18 BDRs não trazem a proporção
A12: Categorias | B12: Colunas "Sugestão — …" seguem a regra decidida para ETFs (description / name / segment). É sugestão: nada decidido para BDR ainda
A13: Dividendos | B13: Não disponíveis no plano gratuito

Sheet BDRs (892)
A1: Ticker | B1: Empresa / fundo | C1: Classe | D1: Sufixo | E1: Setor (pt-BR) | F1: Setor (BRAPI) | G1: Patrocínio (BRAPI) | H1: Lastro | I1: Ações por BDR | J1: BDRs por ação | K1: Preço (R$) | L1: Variação (R$) | M1: Variação dia | N1: Abertura (R$) | O1: Mínima dia (R$) | P1: Máxima dia (R$) | Q1: Fech. anterior (R$) | R1: Volume (BDRs) | S1: Volume financeiro aprox. (R$) | T1: Mín. 52 semanas (R$) | U1: Máx. 52 semanas (R$) | V1: Posição na faixa 52s | W1: Distância da máx. 52s | X1: Valor de mercado da empresa (R$ mi) | Y1: Sugestão — categoria description | Z1: Sugestão — categoria name | AA1: Sugestão — segment | AB1: Observação | AC1: Logo (URL) | AD1: Cotação em
A2: A1AP34 | B2: Advance Auto Parts, Inc. | C2: BDR de ação | D2: 34 | E2: Varejo | F2: Retail Trade | G2: Não patrocinado | H2: Ação | I2: 0.0625 | J2: =IF(I2="","",1/I2) -> 16 | K2: 13.36 | L2: -0.23 | M2: -0.0169 | N2: 13.94 | O2: 13.36 | P2: 13.94 | Q2: 13.36 | R2: 1113 | S2: =K2*R2 -> 14869.68 | T2: 12.9 | U2: 21.3 | V2: =IF(U2-T2=0,"",(K2-T2)/(U2-T2)) -> 0.054761905 | W2: =IF(U2=0,"",K2/U2-1) -> -0.37276995 | X2: 13187 | Y2: Varejo | Z2: VAREJO | AA2: Retail Trade | AC2: https://icons.brapi.dev/icons/A1AP34.svg | AD2: 46288.772
A3: A1CR34 | B3: Amcor PLC | C3: BDR de ação | D3: 34 | E3: Indústria de transformação | F3: Process Industries | G3: Não patrocinado | H3: Ação | I3: 1 | J3: =IF(I3="","",1/I3) -> 1 | K3: 216.92 | L3: -0.66 | M3: -0.003 | N3: 215.88 | O3: 215.88 | P3: 217.36 | Q3: 216.92 | R3: 146 | S3: =K3*R3 -> 31670.32 | T3: 182.02 | U3: 266.06 | V3: =IF(U3-T3=0,"",(K3-T3)/(U3-T3)) -> 0.41527844 | W3: =IF(U3=0,"",K3/U3-1) -> -0.18469518 | X3: 102312 | Y3: Indústria de transformação | Z3: INDUSTRIA_DE_TRANSFORMACAO | AA3: Process Industries | AC3: https://icons.brapi.dev/icons/A1CR34.svg | AD3: 46288.772
A4: A1DC34 | B4: Agree Realty Corp | C4: BDR de ação | D4: 34 | E4: Finanças | F4: Finance | G4: Não patrocinado | H4: Ação | I4: 0.125 | J4: =IF(I4="","",1/I4) -> 8 | K4: 43.31 | L4: 0 | M4: 0 | N4: 43.31 | O4: 43.31 | P4: 43.31 | Q4: 43.31 | R4: 12 | S4: =K4*R4 -> 519.72 | T4: 43.31 | U4: 52.91 | V4: =IF(U4-T4=0,"",(K4-T4)/(U4-T4)) -> 0 | W4: =IF(U4=0,"",K4/U4-1) -> -0.18144018 | X4: 42852 | Y4: Finanças | Z4: FINANCAS | AA4: Finance | AC4: https://icons.brapi.dev/icons/A1DC34.svg | AD4: 46288.772
A5: A1DI34 | B5: Analog Devices Inc | C5: BDR de ação | D5: 34 | E5: Tecnologia eletrônica | F5: Electronic Technology | G5: Não patrocinado | H5: Ação | I5: 0.025 | J5: =IF(I5="","",1/I5) -> 40 | K5: 49.7 | L5: 0.35 | M5: 0.0071 | N5: 49.85 | O5: 49 | P5: 49.85 | Q5: 49.7 | R5: 235 | S5: =K5*R5 -> 11679.5 | T5: 30.85 | U5: 57.288 | V5: =IF(U5-T5=0,"",(K5-T5)/(U5-T5)) -> 0.71298888 | W5: =IF(U5=0,"",K5/U5-1) -> -0.13245357 | X5: 968065 | Y5: Tecnologia eletrônica | Z5: TECNOLOGIA_ELETRONICA | AA5: Electronic Technology | AC5: https://icons.brapi.dev/icons/A1DI34.svg | AD5: 46288.772
A6: A1DM34 | B6: Archer Daniels Midland Company | C6: BDR de ação | D6: 34 | E6: Indústria de transformação | F6: Process Industries | G6: Não patrocinado | H6: Ação | I6: 0.125 | J6: =IF(I6="","",1/I6) -> 8 | K6: 53.45 | L6: 0.44 | M6: 0.0083 | N6: 53.45 | O6: 53.45 | P6: 53.45 | Q6: 53.45 | R6: 9 | S6: =K6*R6 -> 481.05 | T6: 37.2 | U6: 58.03 | V6: =IF(U6-T6=0,"",(K6-T6)/(U6-T6)) -> 0.78012482 | W6: =IF(U6=0,"",K6/U6-1) -> -0.078924694 | X6: 203094 | Y6: Indústria de transformação | Z6: INDUSTRIA_DE_TRANSFORMACAO | AA6: Process Industries | AC6: https://icons.brapi.dev/icons/A1DM34.svg | AD6: 46288.772
A7: A1EG34 | B7: Aegon Ltd. | C7: BDR de ação | D7: 34 | E7: Finanças | F7: Finance | G7: Não patrocinado | H7: ADR | I7: 0.25 | J7: =IF(I7="","",1/I7) -> 4 | K7: 45.65 | L7: 0 | M7: 0 | N7: 45.65 | O7: 45.65 | P7: 45.65 | Q7: 45.65 | R7: 16 | S7: =K7*R7 -> 730.4 | T7: 33.81 | U7: 49.75 | V7: =IF(U7-T7=0,"",(K7-T7)/(U7-T7)) -> 0.74278545 | W7: =IF(U7=0,"",K7/U7-1) -> -0.08241206 | X7: 68553 | Y7: Finanças | Z7: FINANCAS | AA7: Finance | AC7: https://icons.brapi.dev/icons/A1EG34.svg | AD7: 46288.772
A8: A1EP34 | B8: American Electric Power Inc | C8: BDR de ação | D8: 34 | E8: Utilidade pública | F8: Utilities | G8: Não patrocinado | H8: Ação | I8: 0.1 | J8: =IF(I8="","",1/I8) -> 10 | K8: 61.44 | L8: -0.18 | M8: -0.0029 | N8: 60.96 | O8: 60.96 | P8: 61.44 | Q8: 61.44 | R8: 819 | S8: =K8*R8 -> 50319.36 | T8: 59.008 | U8: 72.4 | V8: =IF(U8-T8=0,"",(K8-T8)/(U8-T8)) -> 0.18160096 | W8: =IF(U8=0,"",K8/U8-1) -> -0.15138122 | X8: 335080 | Y8: Utilidade pública | Z8: UTILIDADE_PUBLICA | AA8: Utilities | AC8: https://icons.brapi.dev/icons/A1EP34.svg | AD8: 46288.772
A9: A1ES34 | B9: AES Corporation | C9: BDR de ação | D9: 34 | E9: Utilidade pública | F9: Utilities | G9: Não patrocinado | H9: Ação | I9: 1 | J9: =IF(I9="","",1/I9) -> 1 | K9: 76.24 | L9: 0.56 | M9: 0.0074 | N9: 76.24 | O9: 76.24 | P9: 76.24 | Q9: 76.24 | R9: 1 | S9: =K9*R9 -> 76.24 | T9: 69.65 | U9: 90.63 | V9: =IF(U9-T9=0,"",(K9-T9)/(U9-T9)) -> 0.31410867 | W9: =IF(U9=0,"",K9/U9-1) -> -0.15877745 | X9: 54110 | Y9: Utilidade pública | Z9: UTILIDADE_PUBLICA | AA9: Utilities | AC9: https://icons.brapi.dev/icons/A1ES34.svg | AD9: 46288.772
A10: A1GI34 | B10: Agilent Technologies Inc | C10: BDR de ação | D10: 34 | E10: Tecnologia em saúde | F10: Health Technology | G10: Não patrocinado | H10: Ação | I10: 0.1 | J10: =IF(I10="","",1/I10) -> 10 | K10: 82.5 | L10: 6.74 | M10: 0.089 | N10: 82.24 | O10: 82.24 | P10: 82.55 | Q10: 82.5 | R10: 5066 | S10: =K10*R10 -> 417945 | T10: 54.834 | U10: 82.55 | V10: =IF(U10-T10=0,"",(K10-T10)/(U10-T10)) -> 0.99819599 | W10: =IF(U10=0,"",K10/U10-1) -> -0.00060569352 | X10: 241328 | Y10: Tecnologia em saúde | Z10: TECNOLOGIA_EM_SAUDE | AA10: Health Technology | AC10: https://icons.brapi.dev/icons/A1GI34.svg | AD10: 46288.772
A11: A1GN34 | B11: Allegion PLC | C11: BDR de ação | D11: 34 | E11: Bens de consumo duráveis | F11: Consumer Durables | G11: Não patrocinado | H11: Ação | I11: 0.5 | J11: =IF(I11="","",1/I11) -> 2 | K11: 385.48 | L11: 37.19 | M11: 0.1068 | N11: 388.58 | O11: 385.48 | P11: 388.58 | Q11: 385.48 | R11: 2 | S11: =K11*R11 -> 770.96 | T11: 347.12 | U11: 440.13 | V11: =IF(U11-T11=0,"",(K11-T11)/(U11-T11)) -> 0.41242877 | W11: =IF(U11=0,"",K11/U11-1) -> -0.12416786 | X11: 66998 | Y11: Bens de consumo duráveis | Z11: BENS_DE_CONSUMO_DURAVEIS | AA11: Consumer Durables | AC11: https://icons.brapi.dev/icons/A1GN34.svg | AD11: 46288.772
A12: A1IV34 | B12: Apartment Investment and Management Company -A- | C12: BDR de ação | D12: 34 | E12: Finanças | F12: Finance | G12: Não patrocinado | J12: =IF(I12="","",1/I12) | K12: 11.2 | L12: -0.09 | M12: -0.008 | N12: 11.41 | O12: 10.9 | P12: 11.41 | Q12: 11.2 | R12: 1249 | S12: =K12*R12 -> 13988.8 | T12: 10.9 | U12: 44.5 | V12: =IF(U12-T12=0,"",(K12-T12)/(U12-T12)) -> 0.0089285714 | W12: =IF(U12=0,"",K12/U12-1) -> -0.74831461 | X12: 1605 | Y12: Finanças | Z12: FINANCAS | AA12: Finance | AB12: Proporção não informada pela BRAPI. | AC12: https://icons.brapi.dev/icons/A1IV34.svg | AD12: 46288.772
A13: A1KA34 | B13: Akamai Technologies, Inc. | C13: BDR de ação | D13: 34 | E13: Serviços de tecnologia | F13: Technology Services | G13: Não patrocinado | H13: Ação | I13: 0.0833 | J13: =IF(I13="","",1/I13) -> 12.004802 | K13: 51.4 | L13: 0.71 | M13: 0.014 | N13: 50.45 | O13: 48.94 | P13: 51.6 | Q13: 51.4 | R13: 41961 | S13: =K13*R13 -> 2156795.4 | T13: 32.24 | U13: 68.99 | V13: =IF(U13-T13=0,"",(K13-T13)/(U13-T13)) -> 0.52136054 | W13: =IF(U13=0,"",K13/U13-1) -> -0.25496449 | X13: 87039 | Y13: Serviços de tecnologia | Z13: SERVICOS_DE_TECNOLOGIA | AA13: Technology Services | AC13: https://icons.brapi.dev/icons/A1KA34.svg | AD13: 46288.772
A14: A1LB34 | B14: Albemarle Corporation | C14: BDR de ação | D14: 34 | E14: Indústria de transformação | F14: Process Industries | G14: Não patrocinado | H14: Ação | I14: 0.04166667 | J14: =IF(I14="","",1/I14) -> 23.999998 | K14: 25.25 | L14: 0.34 | M14: 0.0136 | N14: 24.58 | O14: 24.04 | P14: 25.25 | Q14: 24.6 | R14: 2392 | S14: =K14*R14 -> 60398 | T14: 17.6 | U14: 45.15 | V14: =IF(U14-T14=0,"",(K14-T14)/(U14-T14)) -> 0.27767695 | W14: =IF(U14=0,"",K14/U14-1) -> -0.44075305 | X14: 70537 | Y14: Indústria de transformação | Z14: INDUSTRIA_DE_TRANSFORMACAO | AA14: Process Industries | AC14: https://icons.brapi.dev/icons/A1LB34.svg | AD14: 46288.772
A15: A1LG34 | B15: Align Technology, Inc. | C15: BDR de ação | D15: 34 | E15: Tecnologia em saúde | F15: Health Technology | G15: Não patrocinado | J15: =IF(I15="","",1/I15) | K15: 192.28 | L15: -5.89 | M15: -0.0297 | N15: 191.14 | O15: 189.24 | P15: 192.28 | Q15: 192.28 | R15: 6 | S15: =K15*R15 -> 1153.68 | T15: 164.56 | U15: 248.5 | V15: =IF(U15-T15=0,"",(K15-T15)/(U15-T15)) -> 0.33023588 | W15: =IF(U15=0,"",K15/U15-1) -> -0.22623742 | X15: 55730 | Y15: Tecnologia em saúde | Z15: TECNOLOGIA_EM_SAUDE | AA15: Health Technology | AB15: Proporção não informada pela BRAPI. | AC15: https://icons.brapi.dev/icons/A1LG34.svg | AD15: 46288.772
A16: A1LK34 | B16: Alaska Air Group, Inc. | C16: BDR de ação | D16: 34 | E16: Transporte | F16: Transportation | G16: Não patrocinado | H16: Ação | I16: 1 | J16: =IF(I16="","",1/I16) -> 1 | K16: 209.16 | L16: 2.1 | M16: 0.0101 | N16: 207.06 | O16: 207.06 | P16: 209.16 | Q16: 209.16 | R16: 3 | S16: =K16*R16 -> 627.48 | T16: 174.72 | U16: 312 | V16: =IF(U16-T16=0,"",(K16-T16)/(U16-T16)) -> 0.25087413 | W16: =IF(U16=0,"",K16/U16-1) -> -0.32961538 | X16: 23937 | Y16: Transporte | Z16: TRANSPORTE | AA16: Transportation | AC16: https://icons.brapi.dev/icons/A1LK34.svg | AD16: 46288.772
A17: A1LL34 | B17: Bread Financial Holdings, Inc. | C17: BDR de ação | D17: 34 | E17: Finanças | F17: Finance | G17: Não patrocinado | H17: Ação | I17: 0.25 | J17: =IF(I17="","",1/I17) -> 4 | K17: 130.39 | L17: -8.49 | M17: -0.0611 | N17: 130 | O17: 129.98 | P17: 131.04 | Q17: 130.39 | R17: 19 | S17: =K17*R17 -> 2477.41 | T17: 72.3 | U17: 148.5 | V17: =IF(U17-T17=0,"",(K17-T17)/(U17-T17)) -> 0.76233596 | W17: =IF(U17=0,"",K17/U17-1) -> -0.12195286 | X17: 20191 | Y17: Finanças | Z17: FINANCAS | AA17: Finance | AC17: https://icons.brapi.dev/icons/A1LL34.svg | AD17: 46288.772
A18: A1LN34 | B18: Alnylam Pharmaceuticals, Inc | C18: BDR de ação | D18: 34 | E18: Tecnologia em saúde | F18: Health Technology | G18: Não patrocinado | H18: Ação | I18: 0.05 | J18: =IF(I18="","",1/I18) -> 20 | K18: 63.72 | L18: 0.66 | M18: 0.0105 | N18: 63.72 | O18: 63.72 | P18: 63.72 | Q18: 63.72 | R18: 70 | S18: =K18*R18 -> 4460.4 | T18: 50.25 | U18: 132.4 | V18: =IF(U18-T18=0,"",(K18-T18)/(U18-T18)) -> 0.16396835 | W18: =IF(U18=0,"",K18/U18-1) -> -0.51873112 | X18: 172329 | Y18: Tecnologia em saúde | Z18: TECNOLOGIA_EM_SAUDE | AA18: Health Technology | AC18: https://icons.brapi.dev/icons/A1LN34.svg | AD18: 46288.772
A19: A1MD34 | B19: Advanced Micro Devices, Inc. | C19: BDR de ação | D19: 34 | E19: Tecnologia eletrônica | F19: Electronic Technology | G19: Não patrocinado | H19: Ação | I19: 0.125 | J19: =IF(I19="","",1/I19) -> 8 | K19: 396 | L19: -0.85 | M19: -0.0021 | N19: 397.29 | O19: 391.15 | P19: 399.51 | Q19: 396.26 | R19: 36230 | S19: =K19*R19 -> 14347080 | T19: 103.35 | U19: 399.51 | V19: =IF(U19-T19=0,"",(K19-T19)/(U19-T19)) -> 0.9881483 | W19: =IF(U19=0,"",K19/U19-1) -> -0.0087857626 | X19: 5211305 | Y19: Tecnologia eletrônica | Z19: TECNOLOGIA_ELETRONICA | AA19: Electronic Technology | AC19: https://icons.brapi.dev/icons/A1MD34.svg | AD19: 46288.772
A20: A1ME34 | B20: AMETEK, Inc. | C20: BDR de ação | D20: 34 | E20: Bens de produção | F20: Producer Manufacturing | G20: Não patrocinado | J20: =IF(I20="","",1/I20) | K20: 52.05 | L20: 2.45 | M20: 0.0494 | N20: 52.44 | O20: 52.05 | P20: 52.44 | Q20: 52.05 | R20: 201 | S20: =K20*R20 -> 10462.05 | T20: 40.37 | U20: 53.99 | V20: =IF(U20-T20=0,"",(K20-T20)/(U20-T20)) -> 0.85756241 | W20: =IF(U20=0,"",K20/U20-1) -> -0.03593258 | X20: 287938 | Y20: Bens de produção | Z20: BENS_DE_PRODUCAO | AA20: Producer Manufacturing | AB20: Proporção não informada pela BRAPI. | AC20: https://icons.brapi.dev/icons/A1ME34.svg | AD20: 46288.772
A21: A1MP34 | B21: Ameriprise Financial Inc | C21: BDR de ação | D21: 34 | E21: Finanças | F21: Finance | G21: Não patrocinado | H21: Ação | I21: 0.025 | J21: =IF(I21="","",1/I21) -> 40 | K21: 65.58 | L21: -4.56 | M21: -0.065 | N21: 64.46 | O21: 64.46 | P21: 65.58 | Q21: 65.58 | R21: 45 | S21: =K21*R21 -> 2951.1 | T21: 55 | U21: 74.13 | V21: =IF(U21-T21=0,"",(K21-T21)/(U21-T21)) -> 0.55305802 | W21: =IF(U21=0,"",K21/U21-1) -> -0.11533792 | X21: 231624 | Y21: Finanças | Z21: FINANCAS | AA21: Finance | AC21: https://icons.brapi.dev/icons/A1MP34.svg | AD21: 46288.772
A22: A1MT34 | B22: Applied Materials, Inc. | C22: BDR de ação | D22: 34 | E22: Bens de produção | F22: Producer Manufacturing | G22: Não patrocinado | H22: Ação | I22: 0.1 | J22: =IF(I22="","",1/I22) -> 10 | K22: 246 | L22: 4.8 | M22: 0.0199 | N22: 244.1 | O22: 237.45 | P22: 246 | Q22: 244.7 | R22: 4117 | S22: =K22*R22 -> 1012782 | T22: 104.97 | U22: 382.67 | V22: =IF(U22-T22=0,"",(K22-T22)/(U22-T22)) -> 0.5078502 | W22: =IF(U22=0,"",K22/U22-1) -> -0.35714846 | X22: 1918849 | Y22: Bens de produção | Z22: BENS_DE_PRODUCAO | AA22: Producer Manufacturing | AC22: https://icons.brapi.dev/icons/A1MT34.svg | AD22: 46288.772
A23: A1NE34 | B23: Arista Networks Inc | C23: BDR de ação | D23: 34 | E23: Tecnologia eletrônica | F23: Electronic Technology | G23: Não patrocinado | H23: Ação | I23: 0.25 | J23: =IF(I23="","",1/I23) -> 4 | K23: 262.6 | L23: 0.78 | M23: 0.003 | N23: 260.53 | O23: 259.48 | P23: 263.15 | Q23: 262.6 | R23: 435 | S23: =K23*R23 -> 114231 | T23: 151.97 | U23: 272.91 | V23: =IF(U23-T23=0,"",(K23-T23)/(U23-T23)) -> 0.91475112 | W23: =IF(U23=0,"",K23/U23-1) -> -0.037778022 | X23: 1324415 | Y23: Tecnologia eletrônica | Z23: TECNOLOGIA_ELETRONICA | AA23: Electronic Technology | AC23: https://icons.brapi.dev/icons/A1NE34.svg | AD23: 46288.772
A24: A1ON34 | B24: Aon PLC | C24: BDR de ação | D24: 34 | E24: Finanças | F24: Finance | G24: Não patrocinado | H24: Ação | I24: 0.041667 | J24: =IF(I24="","",1/I24) -> 23.999808 | K24: 60.95 | L24: 0.2 | M24: 0.0033 | N24: 60.95 | O24: 60.95 | P24: 60.95 | Q24: 60.95 | R24: 1 | S24: =K24*R24 -> 60.95 | T24: 60.4 | U24: 81.250002 | V24: =IF(U24-T24=0,"",(K24-T24)/(U24-T24)) -> 0.026378895 | W24: =IF(U24=0,"",K24/U24-1) -> -0.24984617 | X24: 310589 | Y24: Finanças | Z24: FINANCAS | AA24: Finance | AC24: https://icons.brapi.dev/icons/A1ON34.svg | AD24: 46288.772
A25: A1PA34 | B25: APA Corporation | C25: BDR de ação | D25: 34 | E25: Energia (petróleo, gás e carvão) | F25: Energy Minerals | G25: Não patrocinado | H25: Ação | I25: 1 | J25: =IF(I25="","",1/I25) -> 1 | K25: 225.94 | L25: 5.59 | M25: 0.0254 | N25: 225.94 | O25: 225.94 | P25: 225.94 | Q25: 225.94 | R25: 6 | S25: =K25*R25 -> 1355.64 | T25: 118 | U25: 234.37 | V25: =IF(U25-T25=0,"",(K25-T25)/(U25-T25)) -> 0.92755865 | W25: =IF(U25=0,"",K25/U25-1) -> -0.035968767 | X25: 75844 | Y25: Energia (petróleo, gás e carvão) | Z25: ENERGIA | AA25: Energy Minerals | AC25: https://icons.brapi.dev/icons/A1PA34.svg | AD25: 46288.772
A26: A1PD34 | B26: Air Products & Chemicals Inc | C26: BDR de ação | D26: 34 | E26: Indústria de transformação | F26: Process Industries | G26: Não patrocinado | H26: Ação | I26: 0.041667 | J26: =IF(I26="","",1/I26) -> 23.999808 | K26: 60.56 | L26: -1.9 | M26: -0.0304 | N26: 60.56 | O26: 60.56 | P26: 60.56 | Q26: 60.56 | R26: 3 | S26: =K26*R26 -> 181.68 | T26: 51.016668 | U26: 66.99 | V26: =IF(U26-T26=0,"",(K26-T26)/(U26-T26)) -> 0.59745406 | W26: =IF(U26=0,"",K26/U26-1) -> -0.095984475 | X26: 328057 | Y26: Indústria de transformação | Z26: INDUSTRIA_DE_TRANSFORMACAO | AA26: Process Industries | AC26: https://icons.brapi.dev/icons/A1PD34.svg | AD26: 46288.772
A27: A1PH34 | B27: Amphenol Corporation (New) | C27: BDR de ação | D27: 34 | E27: Tecnologia eletrônica | F27: Electronic Technology | G27: Não patrocinado | H27: Ação | I27: 0.083333 | J27: =IF(I27="","",1/I27) -> 12.000048 | K27: 35.44 | L27: 0.1 | M27: 0.0028 | N27: 35.63 | O27: 35.05 | P27: 35.63 | Q27: 35.44 | R27: 3940 | S27: =K27*R27 -> 139633.6 | T27: 24.72 | U27: 68.2 | V27: =IF(U27-T27=0,"",(K27-T27)/(U27-T27)) -> 0.24655013 | W27: =IF(U27=0,"",K27/U27-1) -> -0.48035191 | X27: 1045449 | Y27: Tecnologia eletrônica | Z27: TECNOLOGIA_ELETRONICA | AA27: Electronic Technology | AC27: https://icons.brapi.dev/icons/A1PH34.svg | AD27: 46288.772
A28: A1PL34 | B28: Applied Digital Corporation | C28: BDR de ação | D28: 34 | E28: Serviços de tecnologia | F28: Technology Services | G28: Não patrocinado | H28: Ação | I28: 1 | J28: =IF(I28="","",1/I28) -> 1 | K28: 144.6 | L28: -3.1 | M28: -0.021 | N28: 147.75 | O28: 144.15 | P28: 147.75 | Q28: 144.61 | R28: 154 | S28: =K28*R28 -> 22268.4 | T28: 104.36 | U28: 251.81 | V28: =IF(U28-T28=0,"",(K28-T28)/(U28-T28)) -> 0.27290607 | W28: =IF(U28=0,"",K28/U28-1) -> -0.42575752 | X28: 42572 | Y28: Serviços de tecnologia | Z28: SERVICOS_DE_TECNOLOGIA | AA28: Technology Services | AC28: https://icons.brapi.dev/icons/A1PL34.svg | AD28: 46288.772
A29: A1PO34 | B29: Apollo Global Management Inc | C29: BDR de ação | D29: 34 | E29: Finanças | F29: Finance | G29: Não patrocinado | H29: Ação | I29: 0.06666667 | J29: =IF(I29="","",1/I29) -> 14.999999 | K29: 42.81 | L29: 0.52 | M29: 0.0123 | N29: 42.29 | O29: 42.29 | P29: 43.21 | Q29: 42.81 | R29: 875 | S29: =K29*R29 -> 37458.75 | T29: 34.5 | U29: 56.2 | V29: =IF(U29-T29=0,"",(K29-T29)/(U29-T29)) -> 0.38294931 | W29: =IF(U29=0,"",K29/U29-1) -> -0.23825623 | X29: 375210 | Y29: Finanças | Z29: FINANCAS | AA29: Finance | AC29: https://icons.brapi.dev/icons/A1PO34.svg | AD29: 46288.772
A30: A1PP34 | B30: AppLovin Corp. | C30: BDR de ação | D30: 34 | E30: Serviços de tecnologia | F30: Technology Services | G30: (não informado) | H30: Ação | I30: 0.03125 | J30: =IF(I30="","",1/I30) -> 32 | K30: 50.97 | L30: -1.24 | M30: -0.0238 | N30: 52.74 | O30: 49.18 | P30: 52.74 | Q30: 50.97 | R30: 4417 | S30: =K30*R30 -> 225134.49 | T30: 48 | U30: 127.88 | V30: =IF(U30-T30=0,"",(K30-T30)/(U30-T30)) -> 0.037180771 | W30: =IF(U30=0,"",K30/U30-1) -> -0.60142321 | X30: 562998 | Y30: Serviços de tecnologia | Z30: SERVICOS_DE_TECNOLOGIA | AA30: Technology Services | AC30: https://icons.brapi.dev/icons/A1PP34.svg | AD30: 46288.772
A31: A1RC34 | B31: Arcos Dorados Holdings Inc | C31: BDR de ação | D31: 34 | E31: Serviços ao consumidor | F31: Consumer Services | G31: Não patrocinado | H31: Ação | I31: 1 | J31: =IF(I31="","",1/I31) -> 1 | K31: 39.04 | L31: -3.04 | M31: -0.0722 | N31: 39.7 | O31: 39.04 | P31: 39.7 | Q31: 39.04 | R31: 204 | S31: =K31*R31 -> 7964.16 | T31: 35.28 | U31: 46.9 | V31: =IF(U31-T31=0,"",(K31-T31)/(U31-T31)) -> 0.32358003 | W31: =IF(U31=0,"",K31/U31-1) -> -0.16759062 | X31: 8125 | Y31: Serviços ao consumidor | Z31: SERVICOS_AO_CONSUMIDOR | AA31: Consumer Services | AC31: https://icons.brapi.dev/icons/A1RC34.svg | AD31: 46288.772
A32: A1RE34 | B32: Alexandria Real Estate Equities Inc | C32: BDR de ação | D32: 34 | E32: Finanças | F32: Finance | G32: Não patrocinado | H32: Ação | I32: 0.25 | J32: =IF(I32="","",1/I32) -> 4 | K32: 66.98 | L32: -1.9 | M32: -0.0276 | N32: 68.88 | O32: 66.98 | P32: 68.88 | Q32: 66.98 | R32: 2359 | S32: =K32*R32 -> 158005.82 | T32: 49.66 | U32: 116 | V32: =IF(U32-T32=0,"",(K32-T32)/(U32-T32)) -> 0.26107929 | W32: =IF(U32=0,"",K32/U32-1) -> -0.42258621 | X32: 48021 | Y32: Finanças | Z32: FINANCAS | AA32: Finance | AC32: https://icons.brapi.dev/icons/A1RE34.svg | AD32: 46288.772
... A41: A1ZN34 | B41: AstraZeneca PLC | C41: BDR de ação | D41: 34 | E41: Tecnologia em saúde | F41: Health Technology | G41: Não patrocinado | H41: ADR | I41: 0.1666 | J41: =IF(I41="","",1/I41) -> 6.002401 | K41: 140.55 | L41: -8.38 | M41: -0.0563 | N41: 142.21 | O41: 140.55 | P41: 142.96 | Q41: 140.55 | R41: 522 | S41: =K41*R41 -> 73367.1 | T41: 130.02 | U41: 190.4 | V41: =IF(U41-T41=0,"",(K41-T41)/(U41-T41)) -> 0.1743955 | W41: =IF(U41=0,"",K41/U41-1) -> -0.26181723 | X41: 1341611 | Y41: Tecnologia em saúde | Z41: TECNOLOGIA_EM_SAUDE | AA41: Health Technology | AC41: https://icons.brapi.dev/icons/A1ZN34.svg | AD41: 46288.772
A42: A2FY34 | B42: Afya Limited | C42: BDR de ação | D42: 34 | E42: Serviços ao consumidor | F42: Consumer Services | G42: Não patrocinado | J42: =IF(I42="","",1/I42) | K42: 34.83 | L42: -0.03 | M42: -0.0009 | N42: 34.83 | O42: 34.83 | P42: 35.29 | Q42: 34.83 | R42: 2703 | S42: =K42*R42 -> 94145.49 | T42: 34 | U42: 44 | V42: =IF(U42-T42=0,"",(K42-T42)/(U42-T42)) -> 0.083 | W42: =IF(U42=0,"",K42/U42-1) -> -0.20840909 | X42: 6314 | Y42: Serviços ao consumidor | Z42: SERVICOS_AO_CONSUMIDOR | AA42: Consumer Services | AB42: Proporção não informada pela BRAPI. | AC42: https://icons.brapi.dev/icons/A2FY34.svg | AD42: 46288.772
A43: A2MB34 | B43: Ambarella, Inc. | C43: BDR de ação | D43: 34 | E43: Tecnologia eletrônica | F43: Electronic Technology | G43: Não patrocinado | H43: Ação | I43: 0.04 | J43: =IF(I43="","",1/I43) -> 25 | K43: 14.12 | L43: 0.29 | M43: 0.021 | N43: 13.5 | O43: 13.5 | P43: 14.13 | Q43: 14.12 | R43: 447 | S43: =K43*R43 -> 6311.64 | T43: 10.21 | U43: 20.3 | V43: =IF(U43-T43=0,"",(K43-T43)/(U43-T43)) -> 0.38751239 | W43: =IF(U43=0,"",K43/U43-1) -> -0.3044335 | X43: 15149 | Y43: Tecnologia eletrônica | Z43: TECNOLOGIA_ELETRONICA | AA43: Electronic Technology | AC43: https://icons.brapi.dev/icons/A2MB34.svg | AD43: 46288.772
A44: A2RE34 | B44: Ares Management Corporation | C44: BDR de ação | D44: 34 | E44: Finanças | F44: Finance | G44: Não patrocinado | H44: Ação | I44: 0.1 | J44: =IF(I44="","",1/I44) -> 10 | K44: 65.1 | L44: 0.24 | M44: 0.0037 | N44: 65.1 | O44: 65.1 | P44: 65.1 | Q44: 65.1 | R44: 2 | S44: =K44*R44 -> 130.2 | T44: 50 | U44: 94.31 | V44: =IF(U44-T44=0,"",(K44-T44)/(U44-T44)) -> 0.34078086 | W44: =IF(U44=0,"",K44/U44-1) -> -0.30972325 | X44: 142948 | Y44: Finanças | Z44: FINANCAS | AA44: Finance | AC44: https://icons.brapi.dev/icons/A2RE34.svg | AD44: 46288.772
A45: A2RR34 | B45: Arrowhead Pharmaceuticals, Inc. | C45: BDR de ação | D45: 34 | E45: Tecnologia em saúde | F45: Health Technology | G45: Não patrocinado | H45: Ação | I45: 0.125 | J45: =IF(I45="","",1/I45) -> 8 | K45: 45.8 | L45: 0 | M45: 0 | N45: 45.8 | O45: 45.8 | P45: 45.8 | Q45: 45.8 | R45: 5 | S45: =K45*R45 -> 229 | T45: 21.45 | U45: 59.95 | V45: =IF(U45-T45=0,"",(K45-T45)/(U45-T45)) -> 0.63246753 | W45: =IF(U45=0,"",K45/U45-1) -> -0.23603003 | X45: 51948 | Y45: Tecnologia em saúde | Z45: TECNOLOGIA_EM_SAUDE | AA45: Health Technology | AC45: https://icons.brapi.dev/icons/A2RR34.svg | AD45: 46288.772
A46: A2RW34 | B46: Arrows Electronics Inc | C46: BDR de ação | D46: 34 | E46: Distribuição | F46: Distribution Services | G46: Não patrocinado | H46: Ação | I46: 0.066666667 | J46: =IF(I46="","",1/I46) -> 15 | K46: 77.92 | L46: 2.32 | M46: 0.0307 | N46: 75.52 | O46: 75.52 | P46: 78.64 | Q46: 77.92 | R46: 13 | S46: =K46*R46 -> 1012.96 | T46: 38.03 | U46: 81.52 | V46: =IF(U46-T46=0,"",(K46-T46)/(U46-T46)) -> 0.91722235 | W46: =IF(U46=0,"",K46/U46-1) -> -0.044160942 | X46: 57791 | Y46: Distribuição | Z46: DISTRIBUICAO | AA46: Distribution Services | AC46: https://icons.brapi.dev/icons/A2RW34.svg | AD46: 46288.772
A47: A2SO34 | B47: Academy Sports and Outdoors Inc | C47: BDR de ação | D47: 34 | E47: Varejo | F47: Retail Trade | G47: Não patrocinado | H47: Ação | I47: 0.25 | J47: =IF(I47="","",1/I47) -> 4 | K47: 61.86 | L47: -0.3 | M47: -0.0048 | N47: 61.92 | O47: 61.86 | P47: 62.28 | Q47: 61.86 | R47: 3 | S47: =K47*R47 -> 185.58 | T47: 55 | U47: 78.35 | V47: =IF(U47-T47=0,"",(K47-T47)/(U47-T47)) -> 0.29379015 | W47: =IF(U47=0,"",K47/U47-1) -> -0.21046586 | X47: 15600 | Y47: Varejo | Z47: VAREJO | AA47: Retail Trade | AC47: https://icons.brapi.dev/icons/A2SO34.svg | AD47: 46288.772
A48: A2XO34 | B48: Axon Enterprise Inc | C48: BDR de ação | D48: 34 | E48: Tecnologia eletrônica | F48: Electronic Technology | G48: Não patrocinado | H48: Ação | I48: 0.055555556 | J48: =IF(I48="","",1/I48) -> 18 | K48: 129.47 | L48: -0.68 | M48: -0.0052 | N48: 129.47 | O48: 129.47 | P48: 129.47 | Q48: 129.47 | R48: 2 | S48: =K48*R48 -> 258.94 | T48: 94.6 | U48: 227.46 | V48: =IF(U48-T48=0,"",(K48-T48)/(U48-T48)) -> 0.26245672 | W48: =IF(U48=0,"",K48/U48-1) -> -0.43080102 | X48: 190962 | Y48: Tecnologia eletrônica | Z48: TECNOLOGIA_ELETRONICA | AA48: Electronic Technology | AC48: https://icons.brapi.dev/icons/A2XO34.svg | AD48: 46288.772
A49: A2ZT34 | B49: Azenta Inc | C49: BDR de ação | D49: 34 | E49: Serviços de saúde | F49: Health Services | G49: Não patrocinado | H49: Ação | I49: 0.083333333 | J49: =IF(I49="","",1/I49) -> 12 | K49: 14.14 | L49: -0.24 | M49: -0.0167 | N49: 14.14 | O49: 14.14 | P49: 14.14 | Q49: 14.14 | R49: 100 | S49: =K49*R49 -> 1414 | T49: 8.9 | U49: 17.7 | V49: =IF(U49-T49=0,"",(K49-T49)/(U49-T49)) -> 0.59545455 | W49: =IF(U49=0,"",K49/U49-1) -> -0.20112994 | X49: 7686 | Y49: Serviços de saúde | Z49: SERVICOS_DE_SAUDE | AA49: Health Services | AC49: https://icons.brapi.dev/icons/A2ZT34.svg | AD49: 46288.772
A50: AADA39 | B50: 21SHARES CARDANO ETP | C50: BDR de ETF | D50: 39 | E50: Diversos | F50: Miscellaneous | G50: Não patrocinado | H50: ETP | I50: 1 | J50: =IF(I50="","",1/I50) -> 1 | K50: 22.07 | L50: -1.1 | M50: -0.0475 | N50: 22.07 | O50: 22.07 | P50: 22.07 | Q50: 22.07 | R50: 9 | S50: =K50*R50 -> 198.63 | T50: 13.41 | U50: 82.31 | V50: =IF(U50-T50=0,"",(K50-T50)/(U50-T50)) -> 0.1256894 | W50: =IF(U50=0,"",K50/U50-1) -> -0.73186733 | Y50: ETFs no exterior | Z50: ETFS_NO_EXTERIOR | AA50: Miscellaneous | AC50: https://icons.brapi.dev/icons/AADA39.svg | AD50: 46288.772
A51: AALL34 | B51: American Airlines Group Inc. | C51: BDR de ação | D51: 34 | E51: Transporte | F51: Transportation | G51: Não patrocinado | H51: Ação | I51: 1 | J51: =IF(I51="","",1/I51) -> 1 | K51: 69.02 | L51: -0.7 | M51: -0.01 | N51: 69.36 | O51: 68.5 | P51: 69.36 | Q51: 69.02 | R51: 2130 | S51: =K51*R51 -> 147012.6 | T51: 52.78 | U51: 97 | V51: =IF(U51-T51=0,"",(K51-T51)/(U51-T51)) -> 0.36725464 | W51: =IF(U51=0,"",K51/U51-1) -> -0.28845361 | X51: 46108 | Y51: Transporte | Z51: TRANSPORTE | AA51: Transportation | AC51: https://icons.brapi.dev/icons/AALL34.svg | AD51: 46288.772
A52: AAPL34 | B52: Apple Inc. | C52: BDR de ação | D52: 34 | E52: Tecnologia eletrônica | F52: Electronic Technology | G52: Não patrocinado | H52: Ação | I52: 0.05 | J52: =IF(I52="","",1/I52) -> 20 | K52: 87.17 | L52: 0.47 | M52: 0.0054 | N52: 88.05 | O52: 86.41 | P52: 88.25 | Q52: 86.72 | R52: 201114 | S52: =K52*R52 -> 17531107 | T52: 63.42 | U52: 88.51 | V52: =IF(U52-T52=0,"",(K52-T52)/(U52-T52)) -> 0.94659227 | W52: =IF(U52=0,"",K52/U52-1) -> -0.015139532 | X52: 25375499 | Y52: Tecnologia eletrônica | Z52: TECNOLOGIA_ELETRONICA | AA52: Electronic Technology | AC52: https://icons.brapi.dev/icons/AAPL34.svg | AD52: 46288.772
A53: ABBV34 | B53: AbbVie, Inc. | C53: BDR de ação | D53: 34 | E53: Tecnologia em saúde | F53: Health Technology | G53: Não patrocinado | H53: Ação | I53: 0.0625 | J53: =IF(I53="","",1/I53) -> 16 | K53: 85.83 | L53: 0.84 | M53: 0.0099 | N53: 85.13 | O53: 85.13 | P53: 86.4 | Q53: 85.83 | R53: 1424 | S53: =K53*R53 -> 122221.92 | T53: 58.81 | U53: 89.99 | V53: =IF(U53-T53=0,"",(K53-T53)/(U53-T53)) -> 0.86658114 | W53: =IF(U53=0,"",K53/U53-1) -> -0.046227359 | X53: 2398450 | Y53: Tecnologia em saúde | Z53: TECNOLOGIA_EM_SAUDE | AA53: Health Technology | AC53: https://icons.brapi.dev/icons/ABBV34.svg | AD53: 46288.772
A54: ABGD39 | B54: ABRDN PHYSICAL GOLD SHARES ETF | C54: BDR de ETF | D54: 39 | E54: Diversos | F54: Miscellaneous | G54: Não patrocinado | H54: Ação | I54: 0.5 | J54: =IF(I54="","",1/I54) -> 2 | K54: 106.14 | L54: 1.02 | M54: 0.0097 | N54: 106.14 | O54: 106.14 | P54: 106.14 | Q54: 106.14 | R54: 50 | S54: =K54*R54 -> 5307 | T54: 95.58 | U54: 134.23 | V54: =IF(U54-T54=0,"",(K54-T54)/(U54-T54)) -> 0.27322122 | W54: =IF(U54=0,"",K54/U54-1) -> -0.20926767 | Y54: ETFs no exterior | Z54: ETFS_NO_EXTERIOR | AA54: Miscellaneous | AC54: https://icons.brapi.dev/icons/ABGD39.svg | AD54: 46288.772
A55: ABTT34 | B55: Abbott Laboratories | C55: BDR de ação | D55: 34 | E55: Tecnologia em saúde | F55: Health Technology | G55: Não patrocinado | J55: =IF(I55="","",1/I55) | K55: 44.44 | L55: -5.57 | M55: -0.1114 | N55: 44.98 | O55: 44.28 | P55: 44.98 | Q55: 44.44 | R55: 409 | S55: =K55*R55 -> 18175.96 | T55: 33.5 | U55: 61.08 | V55: =IF(U55-T55=0,"",(K55-T55)/(U55-T55)) -> 0.39666425 | W55: =IF(U55=0,"",K55/U55-1) -> -0.2724296 | X55: 918237 | Y55: Tecnologia em saúde | Z55: TECNOLOGIA_EM_SAUDE | AA55: Health Technology | AB55: Proporção não informada pela BRAPI. | AC55: https://icons.brapi.dev/icons/ABTT34.svg | AD55: 46288.772
A56: ABUD34 | B56: Anheuser-Busch InBev SA/NV | C56: BDR de ação | D56: 34 | E56: Bens de consumo não duráveis | F56: Consumer Non-Durables | G56: Não patrocinado | H56: ADR | I56: 0.1667 | J56: =IF(I56="","",1/I56) -> 5.9988002 | K56: 66.64 | L56: 0.43 | M56: 0.0065 | N56: 66.03 | O56: 66.03 | P56: 66.7 | Q56: 66.64 | R56: 3 | S56: =K56*R56 -> 199.92 | T56: 52 | U56: 73.41 | V56: =IF(U56-T56=0,"",(K56-T56)/(U56-T56)) -> 0.68379262 | W56: =IF(U56=0,"",K56/U56-1) -> -0.092221768 | X56: 794275 | Y56: Bens de consumo não duráveis | Z56: BENS_DE_CONSUMO_NAO_DURAVEIS | AA56: Consumer Non-Durables | AC56: https://icons.brapi.dev/icons/ABUD34.svg | AD56: 46288.772
A57: ACNB34 | B57: Accenture PLC | C57: BDR de ação | D57: 34 | E57: Serviços de tecnologia | F57: Technology Services | G57: Não patrocinado | H57: Ação | I57: 1 | J57: =IF(I57="","",1/I57) -> 1 | K57: 955.04 | L57: 11.69 | M57: 0.0124 | N57: 950.34 | O57: 950.34 | P57: 955.04 | Q57: 955.04 | R57: 45 | S57: =K57*R57 -> 42976.8 | T57: 609 | U57: 1564.2 | V57: =IF(U57-T57=0,"",(K57-T57)/(U57-T57)) -> 0.36226968 | W57: =IF(U57=0,"",K57/U57-1) -> -0.38943869 | X57: 575363 | Y57: Serviços de tecnologia | Z57: SERVICOS_DE_TECNOLOGIA | AA57: Technology Services | AC57: https://icons.brapi.dev/icons/ACNB34.svg | AD57: 46288.772
A58: ACWX39 | B58: ISHARES MSCI ACWI EX U.S. ETF | C58: BDR de ETF | D58: 39 | E58: Diversos | F58: Miscellaneous | G58: Não patrocinado | H58: Ação | I58: 0.16666666 | J58: =IF(I58="","",1/I58) -> 6.0000002 | K58: 66.08 | L58: -0.33 | M58: -0.005 | N58: 66 | O58: 66 | P58: 66.08 | Q58: 66.08 | R58: 40 | S58: =K58*R58 -> 2643.2 | T58: 56.01 | U58: 69.99 | V58: =IF(U58-T58=0,"",(K58-T58)/(U58-T58)) -> 0.72031474 | W58: =IF(U58=0,"",K58/U58-1) -> -0.055865124 | Y58: ETFs no exterior | Z58: ETFS_NO_EXTERIOR | AA58: Miscellaneous | AC58: https://icons.brapi.dev/icons/ACWX39.svg | AD58: 46288.772
A59: ADBE34 | B59: Adobe Inc. | C59: BDR de ação | D59: 34 | E59: Serviços de tecnologia | F59: Technology Services | G59: Não patrocinado | H59: Ação | I59: 0.02 | J59: =IF(I59="","",1/I59) -> 50 | K59: 24.85 | L59: 0.61 | M59: 0.0252 | N59: 24.21 | O59: 24.21 | P59: 24.95 | Q59: 24.85 | R59: 58497 | S59: =K59*R59 -> 1453650.4 | T59: 19.48 | U59: 40.27 | V59: =IF(U59-T59=0,"",(K59-T59)/(U59-T59)) -> 0.25829726 | W59: =IF(U59=0,"",K59/U59-1) -> -0.38291532 | X59: 484669 | Y59: Serviços de tecnologia | Z59: SERVICOS_DE_TECNOLOGIA | AA59: Technology Services | AC59: https://icons.brapi.dev/icons/ADBE34.svg | AD59: 46288.772
A60: ADPR34 | B60: Automatic Data Processing, Inc. | C60: BDR de ação | D60: 34 | E60: Serviços de tecnologia | F60: Technology Services | G60: Não patrocinado | H60: Ação | I60: 0.04166667 | J60: =IF(I60="","",1/I60) -> 23.999998 | K60: 57.12 | L60: -0.38 | M60: -0.0066 | N60: 57.12 | O60: 57.12 | P60: 57.12 | Q60: 57.12 | R60: 10 | S60: =K60*R60 -> 571.2 | T60: 39 | U60: 65.23 | V60: =IF(U60-T60=0,"",(K60-T60)/(U60-T60)) -> 0.69081205 | W60: =IF(U60=0,"",K60/U60-1) -> -0.1243293 | X60: 548198 | Y60: Serviços de tecnologia | Z60: SERVICOS_DE_TECNOLOGIA | AA60: Technology Services | AC60: https://icons.brapi.dev/icons/ADPR34.svg | AD60: 46288.772
A61: AIGB34 | B61: American International Group, Inc. | C61: BDR de ação | D61: 34 | E61: Finanças | F61: Finance | G61: Não patrocinado | H61: Ação | I61: 1 | J61: =IF(I61="","",1/I61) -> 1 | K61: 382.2 | L61: -7.83 | M61: -0.0201 | N61: 386 | O61: 382.2 | P61: 386 | Q61: 382.2 | R61: 2 | S61: =K61*R61 -> 764.4 | T61: 365.93 | U61: 483.36 | V61: =IF(U61-T61=0,"",(K61-T61)/(U61-T61)) -> 0.13855063 | W61: =IF(U61=0,"",K61/U61-1) -> -0.209285 | X61: 201183 | Y61: Finanças | Z61: FINANCAS | AA61: Finance | AC61: https://icons.brapi.dev/icons/AIGB34.svg | AD61: 46288.772
A62: AIRB34 | B62: Airbnb, Inc. | C62: BDR de ação | D62: 34 | E62: Serviços ao consumidor | F62: Consumer Services | G62: Não patrocinado | H62: Ação | I62: 0.05 | J62: =IF(I62="","",1/I62) -> 20 | K62: 38.65 | L62: -2.87 | M62: -0.0691 | N62: 41.94 | O62: 38.64 | P62: 41.94 | Q62: 38.65 | R62: 24570 | S62: =K62*R62 -> 949630.5 | T62: 30 | U62: 50.06 | V62: =IF(U62-T62=0,"",(K62-T62)/(U62-T62)) -> 0.43120638 | W62: =IF(U62=0,"",K62/U62-1) -> -0.22792649 | X62: 495852 | Y62: Serviços ao consumidor | Z62: SERVICOS_AO_CONSUMIDOR | AA62: Consumer Services | AC62: https://icons.brapi.dev/icons/AIRB34.svg | AD62: 46288.772
A63: AMGN34 | B63: Amgen Inc. | C63: BDR de ação | D63: 34 | E63: Tecnologia em saúde | F63: Health Technology | G63: Não patrocinado | H63: Ação | I63: 0.03571 | J63: =IF(I63="","",1/I63) -> 28.00336 | K63: 75.4 | L63: 0.42 | M63: 0.0056 | N63: 74.4 | O63: 74.4 | P63: 75.4 | Q63: 75.4 | R63: 15 | S63: =K63*R63 -> 1131 | T63: 48.4 | U63: 83.38 | V63: =IF(U63-T63=0,"",(K63-T63)/(U63-T63)) -> 0.77186964 | W63: =IF(U63=0,"",K63/U63-1) -> -0.095706404 | X63: 1135051 | Y63: Tecnologia em saúde | Z63: TECNOLOGIA_EM_SAUDE | AA63: Health Technology | AC63: https://icons.brapi.dev/icons/AMGN34.svg | AD63: 46288.772
A64: AMZO34 | B64: Amazon.com, Inc. | C64: BDR de ação | D64: 34 | E64: Varejo | F64: Retail Trade | G64: Não patrocinado | H64: Ação | I64: 0.05 | J64: =IF(I64="","",1/I64) -> 20 | K64: 64.82 | L64: -0.56 | M64: -0.0086 | N64: 65.38 | O64: 63.95 | P64: 65.38 | Q64: 64.43 | R64: 696643 | S64: =K64*R64 -> 45156399 | T64: 51.1 | U64: 72.85 | V64: =IF(U64-T64=0,"",(K64-T64)/(U64-T64)) -> 0.6308046 | W64: =IF(U64=0,"",K64/U64-1) -> -0.11022649 | X64: 14075202 | Y64: Varejo | Z64: VAREJO | AA64: Retail Trade | AC64: https://icons.brapi.dev/icons/AMZO34.svg | AD64: 46288.772
A65: ANGV39 | B65: VANECK FALLEN ANGEL HIGH YIELD BOND ETF | C65: BDR de ETF | D65: 39 | E65: Diversos | F65: Miscellaneous | G65: Não patrocinado | H65: Ação | I65: 0.33333333 | J65: =IF(I65="","",1/I65) -> 3 | K65: 48.9 | L65: 0 | M65: 0 | N65: 48.9 | O65: 48.9 | P65: 48.9 | Q65: 48.9 | R65: 7 | S65: =K65*R65 -> 342.3 | T65: 48.25 | U65: 54.65 | V65: =IF(U65-T65=0,"",(K65-T65)/(U65-T65)) -> 0.1015625 | W65: =IF(U65=0,"",K65/U65-1) -> -0.105215 | Y65: ETFs no exterior | Z65: ETFS_NO_EXTERIOR | AA65: Miscellaneous | AC65: https://icons.brapi.dev/icons/ANGV39.svg | AD65: 46288.772
A66: APTV34 | B66: Aptiv PLC | C66: BDR de ação | D66: 34 | E66: Bens de produção | F66: Producer Manufacturing | G66: Não patrocinado | J66: =IF(I66="","",1/I66) | K66: 111.97 | L66: -1.78 | M66: -0.0156 | N66: 111.97 | O66: 111.97 | P66: 111.97 | Q66: 111.97 | R66: 5 | S66: =K66*R66 -> 559.85 | T66: 111.97 | U66: 238.8 | V66: =IF(U66-T66=0,"",(K66-T66)/(U66-T66)) -> 0 | W66: =IF(U66=0,"",K66/U66-1) -> -0.5311139 | X66: 47403 | Y66: Bens de produção | Z66: BENS_DE_PRODUCAO | AA66: Producer Manufacturing | AB66: Proporção não informada pela BRAPI. | AC66: https://icons.brapi.dev/icons/APTV34.svg | AD66: 46288.772
A67: ARGT39 | B67: GLOBAL X MSCI ARGENTINA ETF | C67: BDR de ETF | D67: 39 | E67: Diversos | F67: Miscellaneous | G67: Não patrocinado | H67: Ação | I67: 0.1 | J67: =IF(I67="","",1/I67) -> 10 | K67: 47.02 | L67: -0.23 | M67: -0.0049 | N67: 47.4 | O67: 47 | P67: 47.61 | Q67: 47.02 | R67: 218 | S67: =K67*R67 -> 10250.36 | T67: 35.7 | U67: 53.99 | V67: =IF(U67-T67=0,"",(K67-T67)/(U67-T67)) -> 0.61891744 | W67: =IF(U67=0,"",K67/U67-1) -> -0.12909798 | Y67: ETFs no exterior | Z67: ETFS_NO_EXTERIOR | AA67: Miscellaneous | AC67: https://icons.brapi.dev/icons/ARGT39.svg | AD67: 46288.772
A68: ARMT34 | B68: ArcelorMittal SA | C68: BDR de ação | D68: 34 | E68: Mineração e metais | F68: Non-Energy Minerals | G68: Não patrocinado | J68: =IF(I68="","",1/I68) | K68: 185.25 | L68: -3.23 | M68: -0.0171 | N68: 188.47 | O68: 184.87 | P68: 195.51 | Q68: 185.25 | R68: 1680 | S68: =K68*R68 -> 311220 | T68: 95.3 | U68: 203.5 | V68: =IF(U68-T68=0,"",(K68-T68)/(U68-T68)) -> 0.83133087 | W68: =IF(U68=0,"",K68/U68-1) -> -0.08968059 | X68: 278106 | Y68: Mineração e metais | Z68: MINERACAO_METAIS | AA68: Non-Energy Minerals | AB68: Proporção não informada pela BRAPI. | AC68: https://icons.brapi.dev/icons/ARMT34.svg | AD68: 46288.772
A69: ARNC34 | B69: Howmet Aerospace Inc | C69: BDR de ação | D69: 34 | E69: Tecnologia eletrônica | F69: Electronic Technology | G69: Não patrocinado | H69: Ação | I69: 0.04 | J69: =IF(I69="","",1/I69) -> 25 | K69: 46.13 | L69: -0.59 | M69: -0.0126 | N69: 46 | O69: 45.8 | P69: 46.26 | Q69: 46.13 | R69: 29 | S69: =K69*R69 -> 1337.77 | T69: 40.4276 | U69: 61.18 | V69: =IF(U69-T69=0,"",(K69-T69)/(U69-T69)) -> 0.27478268 | W69: =IF(U69=0,"",K69/U69-1) -> -0.24599542 | X69: 459948 | Y69: Tecnologia eletrônica | Z69: TECNOLOGIA_ELETRONICA | AA69: Electronic Technology | AC69: https://icons.brapi.dev/icons/ARNC34.svg | AD69: 46288.772
A70: ASML34 | B70: ASML Holding NV | C70: BDR de ação | D70: 34 | E70: Tecnologia eletrônica | F70: Electronic Technology | G70: Não patrocinado | J70: =IF(I70="","",1/I70) | K70: 163.6 | L70: 1.3 | M70: 0.008 | N70: 161 | O70: 159.8 | P70: 163.6 | Q70: 163.24 | R70: 17756 | S70: =K70*R70 -> 2904881.6 | T70: 90.9 | U70: 190.5 | V70: =IF(U70-T70=0,"",(K70-T70)/(U70-T70)) -> 0.72991968 | W70: =IF(U70=0,"",K70/U70-1) -> -0.14120735 | X70: 3373374 | Y70: Tecnologia eletrônica | Z70: TECNOLOGIA_ELETRONICA | AA70: Electronic Technology | AB70: Proporção não informada pela BRAPI. | AC70: https://icons.brapi.dev/icons/ASML34.svg | AD70: 46288.772
A71: ATTB34 | B71: AT&T Inc | C71: BDR de ação | D71: 34 | E71: Comunicações | F71: Communications | G71: Não patrocinado | H71: Ação | I71: 0.33334 | J71: =IF(I71="","",1/I71) -> 2.99994 | K71: 43.46 | L71: 0.92 | M71: 0.0216 | N71: 42.8 | O71: 42.8 | P71: 43.7 | Q71: 43.64 | R71: 1950 | S71: =K71*R71 -> 84747 | T71: 32.26 | U71: 51.3 | V71: =IF(U71-T71=0,"",(K71-T71)/(U71-T71)) -> 0.58823529 | W71: =IF(U71=0,"",K71/U71-1) -> -0.15282651 | X71: 880219 | Y71: Comunicações | Z71: COMUNICACOES | AA71: Communications | AC71: https://icons.brapi.dev/icons/ATTB34.svg | AD71: 46288.772
A72: AURA33 | B72: AURA MINERALS INC. | C72: BDR de ação | D72: 33 | E72: Mineração e metais | F72: Non-Energy Minerals | G72: Não patrocinado | H72: Ação | I72: 1 | J72: =IF(I72="","",1/I72) -> 1 | K72: 147.5 | L72: -9.48 | M72: -0.0604 | N72: 154 | O72: 144.11 | P72: 154.01 | Q72: 147.5 | R72: 1080561 | S72: =K72*R72 -> 1.5938275e+08 | T72: 49.9 | U72: 182.95 | V72: =IF(U72-T72=0,"",(K72-T72)/(U72-T72)) -> 0.73355881 | W72: =IF(U72=0,"",K72/U72-1) -> -0.19376879 | X72: 39781 | Y72: Mineração e metais | Z72: MINERACAO_METAIS | AA72: Non-Energy Minerals | AC72: https://icons.brapi.dev/icons/AURA33.svg | AD72: 46288.772
A73: AVGO34 | B73: Broadcom Inc. | C73: BDR de ação | D73: 34 | E73: Tecnologia eletrônica | F73: Electronic Technology | G73: Não patrocinado | H73: Ação | I73: 0.02857 | J73: =IF(I73="","",1/I73) -> 35.00175 | K73: 26.28 | L73: -0.33 | M73: -0.0124 | N73: 26.62 | O73: 26.16 | P73: 26.62 | Q73: 26.26 | R73: 158149 | S73: =K73*R73 -> 4156155.7 | T73: 21.78 | U73: 35.76 | V73: =IF(U73-T73=0,"",(K73-T73)/(U73-T73)) -> 0.32188841 | W73: =IF(U73=0,"",K73/U73-1) -> -0.26510067 | X73: 8905727 | Y73: Tecnologia eletrônica | Z73: TECNOLOGIA_ELETRONICA | AA73: Electronic Technology | AC73: https://icons.brapi.dev/icons/AVGO34.svg | AD73: 46288.772
A74: AXPB34 | B74: American Express Co | C74: BDR de ação | D74: 34 | E74: Finanças | F74: Finance | G74: Não patrocinado | H74: Ação | I74: 0.1 | J74: =IF(I74="","",1/I74) -> 10 | K74: 155.96 | L74: -0.12 | M74: -0.0008 | N74: 157.27 | O74: 155.92 | P74: 157.27 | Q74: 155.96 | R74: 175 | S74: =K74*R74 -> 27293 | T74: 150 | U74: 213.57 | V74: =IF(U74-T74=0,"",(K74-T74)/(U74-T74)) -> 0.093754916 | W74: =IF(U74=0,"",K74/U74-1) -> -0.26974762 | X74: 1054334 | Y74: Finanças | Z74: FINANCAS | AA74: Finance | AC74: https://icons.brapi.dev/icons/AXPB34.svg | AD74: 46288.772
A75: AXRP39 | B75: 21SHARES XRP ETP | C75: BDR de ETF | D75: 39 | E75: Diversos | F75: Miscellaneous | G75: Não patrocinado | H75: ETP | I75: 0.16666667 | J75: =IF(I75="","",1/I75) -> 5.9999999 | K75: 35.49 | L75: 2.59 | M75: 0.0787 | N75: 35.49 | O75: 35.49 | P75: 35.49 | Q75: 35.49 | R75: 7 | S75: =K75*R75 -> 248.43 | T75: 30.5 | U75: 72.2 | V75: =IF(U75-T75=0,"",(K75-T75)/(U75-T75)) -> 0.11966427 | W75: =IF(U75=0,"",K75/U75-1) -> -0.50844875 | Y75: ETFs no exterior | Z75: ETFS_NO_EXTERIOR | AA75: Miscellaneous | AC75: https://icons.brapi.dev/icons/AXRP39.svg | AD75: 46288.772
A76: AZOI34 | B76: AutoZone, Inc. | C76: BDR de ação | D76: 34 | E76: Varejo | F76: Retail Trade | G76: Não patrocinado | J76: =IF(I76="","",1/I76) | K76: 65.94 | L76: -3.08 | M76: -0.0446 | N76: 65.26 | O76: 65.26 | P76: 65.94 | Q76: 65.94 | R76: 10 | S76: =K76*R76 -> 659.4 | T76: 65.26 | U76: 104.29 | V76: =IF(U76-T76=0,"",(K76-T76)/(U76-T76)) -> 0.017422496 | W76: =IF(U76=0,"",K76/U76-1) -> -0.36772461 | X76: 241850 | Y76: Varejo | Z76: VAREJO | AA76: Retail Trade | AB76: Proporção não informada pela BRAPI. | AC76: https://icons.brapi.dev/icons/AZOI34.svg | AD76: 46288.772
A77: B1AM34 | B77: Brookfield Corporation | C77: BDR de ação | D77: 34 | E77: Finanças | F77: Finance | G77: Não patrocinado | H77: Ação | I77: 0.25 | J77: =IF(I77="","",1/I77) -> 4 | K77: 48.19 | L77: -0.35 | M77: -0.0072 | N77: 48.54 | O77: 47.8 | P77: 48.54 | Q77: 48.19 | R77: 10690 | S77: =K77*R77 -> 515151.1 | T77: 47.5 | U77: 70 | V77: =IF(U77-T77=0,"",(K77-T77)/(U77-T77)) -> 0.030666667 | W77: =IF(U77=0,"",K77/U77-1) -> -0.31157143 | X77: 432480 | Y77: Finanças | Z77: FINANCAS | AA77: Finance | AC77: https://icons.brapi.dev/icons/B1AM34.svg | AD77: 46288.772
A78: B1AX34 | B78: Baxter International Inc. | C78: BDR de ação | D78: 34 | E78: Tecnologia em saúde | F78: Health Technology | G78: Não patrocinado | J78: =IF(I78="","",1/I78) | K78: 57.95 | L78: -0.75 | M78: -0.0128 | N78: 57.95 | O78: 57.95 | P78: 57.95 | Q78: 57.95 | R78: 3 | S78: =K78*R78 -> 173.85 | T78: 40.97 | U78: 73.27 | V78: =IF(U78-T78=0,"",(K78-T78)/(U78-T78)) -> 0.52569659 | W78: =IF(U78=0,"",K78/U78-1) -> -0.20908967 | X78: 62653 | Y78: Tecnologia em saúde | Z78: TECNOLOGIA_EM_SAUDE | AA78: Health Technology | AB78: Proporção não informada pela BRAPI. | AC78: https://icons.brapi.dev/icons/B1AX34.svg | AD78: 46288.772
A79: B1BT34 | B79: Truist Financial Corporation | C79: BDR de ação | D79: 34 | E79: Finanças | F79: Finance | G79: Não patrocinado | H79: Ação | I79: 0.25 | J79: =IF(I79="","",1/I79) -> 4 | K79: 61 | L79: -1 | M79: -0.0161 | N79: 61 | O79: 61 | P79: 61 | Q79: 61 | R79: 1 | S79: =K79*R79 -> 61 | T79: 58.75 | U79: 66.8925 | V79: =IF(U79-T79=0,"",(K79-T79)/(U79-T79)) -> 0.27632791 | W79: =IF(U79=0,"",K79/U79-1) -> -0.088089098 | X79: 300530 | Y79: Finanças | Z79: FINANCAS | AA79: Finance | AC79: https://icons.brapi.dev/icons/B1BT34.svg | AD79: 46288.772
A80: B1BW34 | B80: Bath & Body Works, Inc. | C80: BDR de ação | D80: 34 | E80: Varejo | F80: Retail Trade | G80: Não patrocinado | J80: =IF(I80="","",1/I80) | K80: 22.2 | L80: 0 | M80: 0 | N80: 22.21 | O80: 22.2 | P80: 22.21 | Q80: 22.2 | R80: 901 | S80: =K80*R80 -> 20002.2 | T80: 19.55 | U80: 34.8 | V80: =IF(U80-T80=0,"",(K80-T80)/(U80-T80)) -> 0.17377049 | W80: =IF(U80=0,"",K80/U80-1) -> -0.36206897 | X80: 17729 | Y80: Varejo | Z80: VAREJO | AA80: Retail Trade | AB80: Proporção não informada pela BRAPI. | AC80: https://icons.brapi.dev/icons/B1BW34.svg | AD80: 46288.772
A81: B1CS34 | B81: Barclays PLC | C81: BDR de ação | D81: 34 | E81: Finanças | F81: Finance | G81: Não patrocinado | H81: ADR | I81: 1 | J81: =IF(I81="","",1/I81) -> 1 | K81: 125.45 | L81: -2.47 | M81: -0.0193 | N81: 127.01 | O81: 125.45 | P81: 127.01 | Q81: 125.45 | R81: 7 | S81: =K81*R81 -> 878.15 | T81: 104.6 | U81: 147.3 | V81: =IF(U81-T81=0,"",(K81-T81)/(U81-T81)) -> 0.4882904 | W81: =IF(U81=0,"",K81/U81-1) -> -0.14833673 | X81: 424966 | Y81: Finanças | Z81: FINANCAS | AA81: Finance | AC81: https://icons.brapi.dev/icons/B1CS34.svg | AD81: 46288.772
A82: B1DX34 | B82: Becton, Dickinson and Company | C82: BDR de ação | D82: 34 | E82: Tecnologia em saúde | F82: Health Technology | G82: Não patrocinado | H82: Ação | I82: 0.2 | J82: =IF(I82="","",1/I82) -> 5 | K82: 186.3 | L82: 2.57 | M82: 0.014 | N82: 186.3 | O82: 186.3 | P82: 186.3 | Q82: 186.3 | R82: 2 | S82: =K82*R82 -> 372.6 | T82: 139.29 | U82: 242.96 | V82: =IF(U82-T82=0,"",(K82-T82)/(U82-T82)) -> 0.45345809 | W82: =IF(U82=0,"",K82/U82-1) -> -0.23320711 | X82: 255101 | Y82: Tecnologia em saúde | Z82: TECNOLOGIA_EM_SAUDE | AA82: Health Technology | AC82: https://icons.brapi.dev/icons/B1DX34.svg | AD82: 46288.772
A83: B1FC34 | B83: Brown-Forman Corporation | C83: BDR de ação | D83: 34 | E83: Bens de consumo não duráveis | F83: Consumer Non-Durables | G83: Não patrocinado | H83: Ação | I83: 1 | J83: =IF(I83="","",1/I83) -> 1 | K83: 136.06 | L83: -0.02 | M83: -0.0001 | N83: 136.06 | O83: 136.06 | P83: 136.06 | Q83: 136.06 | R83: 2 | S83: =K83*R83 -> 272.12 | T83: 118.08 | U83: 167.45 | V83: =IF(U83-T83=0,"",(K83-T83)/(U83-T83)) -> 0.36418878 | W83: =IF(U83=0,"",K83/U83-1) -> -0.18745894 | X83: 62699 | Y83: Bens de consumo não duráveis | Z83: BENS_DE_CONSUMO_NAO_DURAVEIS | AA83: Consumer Non-Durables | AC83: https://icons.brapi.dev/icons/B1FC34.svg | AD83: 46288.772
A84: B1IL34 | B84: Bilibili Inc. | C84: BDR de ação | D84: 34 | E84: Serviços de tecnologia | F84: Technology Services | G84: Não patrocinado | H84: ADR | I84: 0.2 | J84: =IF(I84="","",1/I84) -> 5 | K84: 15.51 | L84: -0.03 | M84: -0.0019 | N84: 15.6 | O84: 15.48 | P84: 15.6 | Q84: 15.51 | R84: 99 | S84: =K84*R84 -> 1535.49 | T84: 14.88 | U84: 38 | V84: =IF(U84-T84=0,"",(K84-T84)/(U84-T84)) -> 0.027249135 | W84: =IF(U84=0,"",K84/U84-1) -> -0.59184211 | X84: 32364 | Y84: Serviços de tecnologia | Z84: SERVICOS_DE_TECNOLOGIA | AA84: Technology Services | AC84: https://icons.brapi.dev/icons/B1IL34.svg | AD84: 46288.772
A85: B1KR34 | B85: Baker Hughes Company Class A | C85: BDR de ação | D85: 34 | E85: Serviços industriais | F85: Industrial Services | G85: Não patrocinado | H85: Ação | I85: 1 | J85: =IF(I85="","",1/I85) -> 1 | K85: 293.77 | L85: 2.03 | M85: 0.007 | N85: 293.77 | O85: 293.77 | P85: 293.77 | Q85: 293.77 | R85: 50 | S85: =K85*R85 -> 14688.5 | T85: 243.6 | U85: 348.4 | V85: =IF(U85-T85=0,"",(K85-T85)/(U85-T85)) -> 0.47872137 | W85: =IF(U85=0,"",K85/U85-1) -> -0.15680253 | X85: 290893 | Y85: Serviços industriais | Z85: SERVICOS_INDUSTRIAIS | AA85: Industrial Services | AC85: https://icons.brapi.dev/icons/B1KR34.svg | AD85: 46288.772
A86: B1LL34 | B86: Ball Corporation | C86: BDR de ação | D86: 34 | E86: Indústria de transformação | F86: Process Industries | G86: Não patrocinado | J86: =IF(I86="","",1/I86) | K86: 162.17 | L86: -0.34 | M86: -0.0021 | N86: 162.17 | O86: 162.17 | P86: 162.17 | Q86: 162.17 | R86: 2 | S86: =K86*R86 -> 324.34 | T86: 123.3 | U86: 166.26 | V86: =IF(U86-T86=0,"",(K86-T86)/(U86-T86)) -> 0.90479516 | W86: =IF(U86=0,"",K86/U86-1) -> -0.024600024 | X86: 81240 | Y86: Indústria de transformação | Z86: INDUSTRIA_DE_TRANSFORMACAO | AA86: Process Industries | AB86: Proporção não informada pela BRAPI. | AC86: https://icons.brapi.dev/icons/B1LL34.svg | AD86: 46288.772
A87: B1ME34 | B87: BeOne Medicines Ltd. | C87: BDR de ação | D87: 34 | E87: Tecnologia em saúde | F87: Health Technology | G87: Não patrocinado | H87: ADR | I87: 0.04 | J87: =IF(I87="","",1/I87) -> 25 | K87: 72.73 | L87: -1.27 | M87: -0.0172 | N87: 73.29 | O87: 72.73 | P87: 73.29 | Q87: 72.73 | R87: 42 | S87: =K87*R87 -> 3054.66 | T87: 54 | U87: 74 | V87: =IF(U87-T87=0,"",(K87-T87)/(U87-T87)) -> 0.9365 | W87: =IF(U87=0,"",K87/U87-1) -> -0.017162162 | X87: 210156 | Y87: Tecnologia em saúde | Z87: TECNOLOGIA_EM_SAUDE | AA87: Health Technology | AC87: https://icons.brapi.dev/icons/B1ME34.svg | AD87: 46288.772
A88: B1MR34 | B88: Biomarin Pharmaceutical Inc. | C88: BDR de ação | D88: 34 | E88: Tecnologia em saúde | F88: Health Technology | G88: Não patrocinado | H88: Ação | I88: 0.5 | J88: =IF(I88="","",1/I88) -> 2 | K88: 159.52 | L88: -4.31 | M88: -0.0263 | N88: 159.53 | O88: 159.52 | P88: 159.53 | Q88: 159.52 | R88: 300 | S88: =K88*R88 -> 47856 | T88: 123.51 | U88: 174.41 | V88: =IF(U88-T88=0,"",(K88-T88)/(U88-T88)) -> 0.70746562 | W88: =IF(U88=0,"",K88/U88-1) -> -0.085373545 | X88: 62778 | Y88: Tecnologia em saúde | Z88: TECNOLOGIA_EM_SAUDE | AA88: Health Technology | AC88: https://icons.brapi.dev/icons/B1MR34.svg | AD88: 46288.772
A89: B1NT34 | B89: BioNTech SE | C89: BDR de ação | D89: 34 | E89: Tecnologia em saúde | F89: Health Technology | G89: Não patrocinado | H89: ADR | I89: 0.0625 | J89: =IF(I89="","",1/I89) -> 16 | K89: 31.86 | L89: -0.45 | M89: -0.0139 | N89: 31.86 | O89: 31.86 | P89: 31.86 | Q89: 31.86 | R89: 8 | S89: =K89*R89 -> 254.88 | T89: 25.78 | U89: 41 | V89: =IF(U89-T89=0,"",(K89-T89)/(U89-T89)) -> 0.39947438 | W89: =IF(U89=0,"",K89/U89-1) -> -0.22292683 | X89: 129678 | Y89: Tecnologia em saúde | Z89: TECNOLOGIA_EM_SAUDE | AA89: Health Technology | AC89: https://icons.brapi.dev/icons/B1NT34.svg | AD89: 46288.772
A90: B1PP34 | B90: BP PLC | C90: BDR de ação | D90: 34 | E90: Energia (petróleo, gás e carvão) | F90: Energy Minerals | G90: Não patrocinado | H90: ADR | I90: 0.25 | J90: =IF(I90="","",1/I90) -> 4 | K90: 57.5 | L90: 1.54 | M90: 0.0275 | N90: 57 | O90: 57 | P90: 57.5 | Q90: 57.5 | R90: 126 | S90: =K90*R90 -> 7245 | T90: 44.17 | U90: 63.12 | V90: =IF(U90-T90=0,"",(K90-T90)/(U90-T90)) -> 0.70343008 | W90: =IF(U90=0,"",K90/U90-1) -> -0.089036755 | X90: 572050 | Y90: Energia (petróleo, gás e carvão) | Z90: ENERGIA | AA90: Energy Minerals | AC90: https://icons.brapi.dev/icons/B1PP34.svg | AD90: 46288.772
A91: B1RF34 | B91: Broadridge Financial Solutions, Inc. | C91: BDR de ação | D91: 34 | E91: Serviços de tecnologia | F91: Technology Services | G91: Não patrocinado | H91: Ação | I91: 0.25 | J91: =IF(I91="","",1/I91) -> 4 | K91: 216 | L91: -20.68 | M91: -0.0874 | N91: 216.44 | O91: 216 | P91: 216.44 | Q91: 216 | R91: 46 | S91: =K91*R91 -> 9936 | T91: 179.67 | U91: 317.6 | V91: =IF(U91-T91=0,"",(K91-T91)/(U91-T91)) -> 0.26339448 | W91: =IF(U91=0,"",K91/U91-1) -> -0.31989924 | X91: 95127 | Y91: Serviços de tecnologia | Z91: SERVICOS_DE_TECNOLOGIA | AA91: Technology Services | AC91: https://icons.brapi.dev/icons/B1RF34.svg | AD91: 46288.772
A92: B1SA34 | B92: Banco Santander-Chile | C92: BDR de ação | D92: 34 | E92: Finanças | F92: Finance | G92: Não patrocinado | H92: ADR | I92: 0.5 | J92: =IF(I92="","",1/I92) -> 2 | K92: 88.83 | L92: 0 | M92: 0 | N92: 88.83 | O92: 88.83 | P92: 88.83 | Q92: 88.83 | R92: 22 | S92: =K92*R92 -> 1954.26 | T92: 69.65 | U92: 96.9 | V92: =IF(U92-T92=0,"",(K92-T92)/(U92-T92)) -> 0.70385321 | W92: =IF(U92=0,"",K92/U92-1) -> -0.083281734 | X92: 84209 | Y92: Finanças | Z92: FINANCAS | AA92: Finance | AC92: https://icons.brapi.dev/icons/B1SA34.svg | AD92: 46288.772
A93: B1SX34 | B93: Boston Scientific Corp | C93: BDR de ação | D93: 34 | E93: Tecnologia em saúde | F93: Health Technology | G93: Não patrocinado | H93: Ação | I93: 0.25 | J93: =IF(I93="","",1/I93) -> 4 | K93: 57.41 | L93: 1.79 | M93: 0.0322 | N93: 57.41 | O93: 57.41 | P93: 57.41 | Q93: 57.41 | R93: 4 | S93: =K93*R93 -> 229.64 | T93: 50.2875 | U93: 140.9075 | V93: =IF(U93-T93=0,"",(K93-T93)/(U93-T93)) -> 0.07859744 | W93: =IF(U93=0,"",K93/U93-1) -> -0.59256959 | X93: 333160 | Y93: Tecnologia em saúde | Z93: TECNOLOGIA_EM_SAUDE | AA93: Health Technology | AC93: https://icons.brapi.dev/icons/B1SX34.svg | AD93: 46288.772
A94: B1TI34 | B94: British American Tobacco PLC | C94: BDR de ação | D94: 34 | E94: Bens de consumo não duráveis | F94: Consumer Non-Durables | G94: Não patrocinado | H94: ADR | I94: 0.2 | J94: =IF(I94="","",1/I94) -> 5 | K94: 57.68 | L94: 0.51 | M94: 0.0089 | N94: 57.17 | O94: 56.85 | P94: 58.08 | Q94: 57.68 | R94: 162 | S94: =K94*R94 -> 9344.16 | T94: 53.7 | U94: 68.75 | V94: =IF(U94-T94=0,"",(K94-T94)/(U94-T94)) -> 0.26445183 | W94: =IF(U94=0,"",K94/U94-1) -> -0.16101818 | X94: 611965 | Y94: Bens de consumo não duráveis | Z94: BENS_DE_CONSUMO_NAO_DURAVEIS | AA94: Consumer Non-Durables | AC94: https://icons.brapi.dev/icons/B1TI34.svg | AD94: 46288.772
A95: B1ZE34 | B95: Braze, Inc. | C95: BDR de ação | D95: 34 | E95: Serviços de tecnologia | F95: Technology Services | G95: Não patrocinado | J95: =IF(I95="","",1/I95) | K95: 63.63 | L95: -1.12 | M95: -0.0173 | N95: 63.63 | O95: 63.63 | P95: 63.63 | Q95: 63.63 | R95: 110 | S95: =K95*R95 -> 6999.3 | T95: 47.4 | U95: 87.2 | V95: =IF(U95-T95=0,"",(K95-T95)/(U95-T95)) -> 0.40778894 | W95: =IF(U95=0,"",K95/U95-1) -> -0.27029817 | X95: 14835 | Y95: Serviços de tecnologia | Z95: SERVICOS_DE_TECNOLOGIA | AA95: Technology Services | AB95: Proporção não informada pela BRAPI. | AC95: https://icons.brapi.dev/icons/B1ZE34.svg | AD95: 46288.772
A96: B2AP34 | B96: Credicorp Ltd. | C96: BDR de ação | D96: 34 | E96: Finanças | F96: Finance | G96: Não patrocinado | H96: Ação | I96: 0.0833333 | J96: =IF(I96="","",1/I96) -> 12.000005 | K96: 167.28 | L96: 2.33 | M96: 0.0141 | N96: 167.79 | O96: 167.28 | P96: 167.79 | Q96: 167.28 | R96: 51 | S96: =K96*R96 -> 8531.28 | T96: 103 | U96: 168.8 | V96: =IF(U96-T96=0,"",(K96-T96)/(U96-T96)) -> 0.9768997 | W96: =IF(U96=0,"",K96/U96-1) -> -0.0090047393 | X96: 159822 | Y96: Finanças | Z96: FINANCAS | AA96: Finance | AC96: https://icons.brapi.dev/icons/B2AP34.svg | AD96: 46288.772
A97: B2HI34 | B97: BILL Holdings, Inc. | C97: BDR de ação | D97: 34 | E97: Serviços de tecnologia | F97: Technology Services | G97: Não patrocinado | J97: =IF(I97="","",1/I97) | K97: 1.33 | L97: 0.01 | M97: 0.0076 | N97: 1.34 | O97: 1.3 | P97: 1.34 | Q97: 1.33 | R97: 330 | S97: =K97*R97 -> 438.9 | T97: 0.9 | U97: 1.77 | V97: =IF(U97-T97=0,"",(K97-T97)/(U97-T97)) -> 0.49425287 | W97: =IF(U97=0,"",K97/U97-1) -> -0.24858757 | X97: 20289 | Y97: Serviços de tecnologia | Z97: SERVICOS_DE_TECNOLOGIA | AA97: Technology Services | AB97: Proporção não informada pela BRAPI. | AC97: https://icons.brapi.dev/icons/B2HI34.svg | AD97: 46288.772
A98: B2LN34 | B98: BlackLine, Inc. | C98: BDR de ação | D98: 34 | E98: Serviços de tecnologia | F98: Technology Services | G98: Não patrocinado | H98: Ação | I98: 0.083333 | J98: =IF(I98="","",1/I98) -> 12.000048 | K98: 11.86 | L98: -0.34 | M98: -0.0279 | N98: 11.93 | O98: 11.86 | P98: 11.93 | Q98: 11.86 | R98: 16 | S98: =K98*R98 -> 189.76 | T98: 11.69 | U98: 26.5 | V98: =IF(U98-T98=0,"",(K98-T98)/(U98-T98)) -> 0.011478731 | W98: =IF(U98=0,"",K98/U98-1) -> -0.55245283 | X98: 8284 | Y98: Serviços de tecnologia | Z98: SERVICOS_DE_TECNOLOGIA | AA98: Technology Services | AC98: https://icons.brapi.dev/icons/B2LN34.svg | AD98: 46288.772
A99: B2MB34 | B99: Bumble, Inc. | C99: BDR de ação | D99: 34 | E99: Serviços de tecnologia | F99: Technology Services | G99: Não patrocinado | J99: =IF(I99="","",1/I99) | K99: 2.87 | L99: -0.05 | M99: -0.0171 | N99: 2.86 | O99: 2.86 | P99: 2.87 | Q99: 2.87 | R99: 19 | S99: =K99*R99 -> 54.53 | T99: 2.61 | U99: 7.55 | V99: =IF(U99-T99=0,"",(K99-T99)/(U99-T99)) -> 0.052631579 | W99: =IF(U99=0,"",K99/U99-1) -> -0.61986755 | X99: 1911 | Y99: Serviços de tecnologia | Z99: SERVICOS_DE_TECNOLOGIA | AA99: Technology Services | AB99: Proporção não informada pela BRAPI. | AC99: https://icons.brapi.dev/icons/B2MB34.svg | AD99: 46288.772
A100: B2RK34 | B100: Bruker Corporation | C100: BDR de ação | D100: 34 | E100: Tecnologia em saúde | F100: Health Technology | G100: Não patrocinado | H100: Ação | I100: 0.1 | J100: =IF(I100="","",1/I100) -> 10 | K100: 30.84 | L100: 0.84 | M100: 0.028 | N100: 30.84 | O100: 30.84 | P100: 30.84 | Q100: 30.84 | R100: 9 | S100: =K100*R100 -> 277.56 | T100: 16.34 | U100: 30.9 | V100: =IF(U100-T100=0,"",(K100-T100)/(U100-T100)) -> 0.99587912 | W100: =IF(U100=0,"",K100/U100-1) -> -0.0019417476 | X100: 47727 | Y100: Tecnologia em saúde | Z100: TECNOLOGIA_EM_SAUDE | AA100: Health Technology | AC100: https://icons.brapi.dev/icons/B2RK34.svg | AD100: 46288.772
A101: B2UR34 | B101: Burlington Stores, Inc. | C101: BDR de ação | D101: 34 | E101: Varejo | F101: Retail Trade | G101: Não patrocinado | H101: Ação | I101: 0.033333 | J101: =IF(I101="","",1/I101) -> 30.0003 | K101: 41.13 | L101: 0 | M101: 0 | N101: 41.13 | O101: 41.13 | P101: 41.13 | Q101: 41.13 | R101: 3 | S101: =K101*R101 -> 123.39 | T101: 41.13 | U101: 56.5 | V101: =IF(U101-T101=0,"",(K101-T101)/(U101-T101)) -> 0 | W101: =IF(U101=0,"",K101/U101-1) -> -0.2720354 | X101: 82570 | Y101: Varejo | Z101: VAREJO | AA101: Retail Trade | AC101: https://icons.brapi.dev/icons/B2UR34.svg | AD101: 46288.772
A102: B2YN34 | B102: Beyond Meat, Inc. | C102: BDR de ação | D102: 34 | E102: Bens de consumo não duráveis | F102: Consumer Non-Durables | G102: Não patrocinado | H102: Ação | I102: 0.05 | J102: =IF(I102="","",1/I102) -> 20 | K102: 52.02 | L102: -7.04 | M102: -0.1192 | N102: 57.52 | O102: 50.66 | P102: 58 | Q102: 52.02 | R102: 1062 | S102: =K102*R102 -> 55245.24 | T102: 50.04 | U102: 1143 | V102: =IF(U102-T102=0,"",(K102-T102)/(U102-T102)) -> 0.0018115942 | W102: =IF(U102=0,"",K102/U102-1) -> -0.95448819 | X102: 1013 | Y102: Bens de consumo não duráveis | Z102: BENS_DE_CONSUMO_NAO_DURAVEIS | AA102: Consumer Non-Durables | AC102: https://icons.brapi.dev/icons/B2YN34.svg | AD102: 46288.772
A103: BAAX39 | B103: ISHARES MSCI ALL COUNTRY ASIA EX JAPAN ETF | C103: BDR de ETF | D103: 39 | E103: Diversos | F103: Miscellaneous | G103: Não patrocinado | H103: Ação | I103: 0.1 | J103: =IF(I103="","",1/I103) -> 10 | K103: 61 | L103: -0.3 | M103: -0.0049 | N103: 61.92 | O103: 60.92 | P103: 61.92 | Q103: 61 | R103: 917 | S103: =K103*R103 -> 55937 | T103: 47.31 | U103: 65.24 | V103: =IF(U103-T103=0,"",(K103-T103)/(U103-T103)) -> 0.76352482 | W103: =IF(U103=0,"",K103/U103-1) -> -0.064990803 | Y103: ETFs no exterior | Z103: ETFS_NO_EXTERIOR | AA103: Miscellaneous | AC103: https://icons.brapi.dev/icons/BAAX39.svg | AD103: 46288.772
A104: BABA34 | B104: Alibaba Group Holding Limited | C104: BDR de ação | D104: 34 | E104: Varejo | F104: Retail Trade | G104: Não patrocinado | H104: ADR | I104: 0.03571 | J104: =IF(I104="","",1/I104) -> 28.00336 | K104: 20.38 | L104: -0.75 | M104: -0.0355 | N104: 20.6 | O104: 20.38 | P104: 20.6 | Q104: 20.49 | R104: 447987 | S104: =K104*R104 -> 9129975.1 | T104: 16.99 | U104: 36.68 | V104: =IF(U104-T104=0,"",(K104-T104)/(U104-T104)) -> 0.17216861 | W104: =IF(U104=0,"",K104/U104-1) -> -0.44438386 | X104: 1488958 | Y104: Varejo | Z104: VAREJO | AA104: Retail Trade | AC104: https://icons.brapi.dev/icons/BABA34.svg | AD104: 46288.772
A105: BACW39 | B105: ISHARES MSCI ACWI ETF | C105: BDR de ETF | D105: 39 | E105: Diversos | F105: Miscellaneous | G105: Não patrocinado | H105: Ação | I105: 0.1 | J105: =IF(I105="","",1/I105) -> 10 | K105: 83 | L105: 0.05 | M105: 0.0006 | N105: 82.82 | O105: 82.79 | P105: 83 | Q105: 83 | R105: 344 | S105: =K105*R105 -> 28552 | T105: 70.39 | U105: 86.79 | V105: =IF(U105-T105=0,"",(K105-T105)/(U105-T105)) -> 0.76890244 | W105: =IF(U105=0,"",K105/U105-1) -> -0.043668625 | Y105: ETFs no exterior | Z105: ETFS_NO_EXTERIOR | AA105: Miscellaneous | AC105: https://icons.brapi.dev/icons/BACW39.svg | AD105: 46288.772
A106: BAER39 | B106: ISHARES US AEROSPACE & DEFENSE ETF | C106: BDR de ETF | D106: 39 | E106: Diversos | F106: Miscellaneous | G106: Não patrocinado | H106: Ação | I106: 0.05 | J106: =IF(I106="","",1/I106) -> 20 | K106: 55.33 | L106: 0.82 | M106: 0.015 | N106: 54.89 | O106: 54.89 | P106: 55.51 | Q106: 55.37 | R106: 2183 | S106: =K106*R106 -> 120785.39 | T106: 51.94 | U106: 75 | V106: =IF(U106-T106=0,"",(K106-T106)/(U106-T106)) -> 0.14700781 | W106: =IF(U106=0,"",K106/U106-1) -> -0.26226667 | Y106: ETFs no exterior | Z106: ETFS_NO_EXTERIOR | AA106: Miscellaneous | AC106: https://icons.brapi.dev/icons/BAER39.svg | AD106: 46288.772
A107: BAGG39 | B107: ISHARES CORE U.S. AGGREGATE BOND ETF | C107: BDR de ETF | D107: 39 | E107: Diversos | F107: Miscellaneous | G107: Não patrocinado | H107: Ação | I107: 0.1 | J107: =IF(I107="","",1/I107) -> 10 | K107: 49.3 | L107: 0.15 | M107: 0.0031 | N107: 49.3 | O107: 49.25 | P107: 49.3 | Q107: 49.3 | R107: 10 | S107: =K107*R107 -> 493 | T107: 42.01 | U107: 56.45 | V107: =IF(U107-T107=0,"",(K107-T107)/(U107-T107)) -> 0.50484765 | W107: =IF(U107=0,"",K107/U107-1) -> -0.12666076 | Y107: ETFs no exterior | Z107: ETFS_NO_EXTERIOR | AA107: Miscellaneous | AC107: https://icons.brapi.dev/icons/BAGG39.svg | AD107: 46288.772
A108: BAIQ39 | B108: GLOBAL X ARTIFICIAL INTELLIGENCE & TECHNOLOGY ETF | C108: BDR de ETF | D108: 39 | E108: Diversos | F108: Miscellaneous | G108: Não patrocinado | H108: Ação | I108: 0.1666666 | J108: =IF(I108="","",1/I108) -> 6.0000024 | K108: 56.86 | L108: 0.09 | M108: 0.0016 | N108: 55.76 | O108: 55.76 | P108: 56.94 | Q108: 56.86 | R108: 18263 | S108: =K108*R108 -> 1038434.2 | T108: 22.25 | U108: 64.6 | V108: =IF(U108-T108=0,"",(K108-T108)/(U108-T108)) -> 0.81723731 | W108: =IF(U108=0,"",K108/U108-1) -> -0.11981424 | Y108: ETFs no exterior | Z108: ETFS_NO_EXTERIOR | AA108: Miscellaneous | AC108: https://icons.brapi.dev/icons/BAIQ39.svg | AD108: 46288.772
...

Sheet Resumo
A1: Por classe
A2: Classe | B2: Qtd. | C2: Volume financeiro aprox. (R$)
A3: BDR de ação | B3: =COUNTIF('BDRs (892)'!$C$2:$C$893,A3) -> 668 | C3: =SUMIF('BDRs (892)'!$C$2:$C$893,A3,'BDRs (892)'!$S$2:$S$893) -> 1.6592861e+09
A4: BDR de ETF | B4: =COUNTIF('BDRs (892)'!$C$2:$C$893,A4) -> 223 | C4: =SUMIF('BDRs (892)'!$C$2:$C$893,A4,'BDRs (892)'!$S$2:$S$893) -> 34417681
A5: Unit de BDR | B5: =COUNTIF('BDRs (892)'!$C$2:$C$893,A5) -> 1 | C5: =SUMIF('BDRs (892)'!$C$2:$C$893,A5,'BDRs (892)'!$S$2:$S$893) -> 351
A6: Total | B6: =SUM(B3:B5) -> 892 | C6: =SUM(C3:C5) -> 1.6937042e+09
A8: BDRs de ação por setor
A9: Setor (pt-BR) | B9: Qtd. | C9: Volume financeiro aprox. (R$)
A10: Finanças | B10: =COUNTIFS('BDRs (892)'!$C$2:$C$893,"BDR de ação",'BDRs (892)'!$E$2:$E$893,A10) -> 125 | C10: =SUMIFS('BDRs (892)'!$S$2:$S$893,'BDRs (892)'!$C$2:$C$893,"BDR de ação",'BDRs (892)'!$E$2:$E$893,A10) -> 3.7458288e+08
A11: Serviços de tecnologia | B11: =COUNTIFS('BDRs (892)'!$C$2:$C$893,"BDR de ação",'BDRs (892)'!$E$2:$E$893,A11) -> 108 | C11: =SUMIFS('BDRs (892)'!$S$2:$S$893,'BDRs (892)'!$C$2:$C$893,"BDR de ação",'BDRs (892)'!$E$2:$E$893,A11) -> 3.0511285e+08
A12: Tecnologia eletrônica | B12: =COUNTIFS('BDRs (892)'!$C$2:$C$893,"BDR de ação",'BDRs (892)'!$E$2:$E$893,A12) -> 63 | C12: =SUMIFS('BDRs (892)'!$S$2:$S$893,'BDRs (892)'!$C$2:$C$893,"BDR de ação",'BDRs (892)'!$E$2:$E$893,A12) -> 2.5859676e+08
A13: Tecnologia em saúde | B13: =COUNTIFS('BDRs (892)'!$C$2:$C$893,"BDR de ação",'BDRs (892)'!$E$2:$E$893,A13) -> 59 | C13: =SUMIFS('BDRs (892)'!$S$2:$S$893,'BDRs (892)'!$C$2:$C$893,"BDR de ação",'BDRs (892)'!$E$2:$E$893,A13) -> 11557487
A14: Varejo | B14: =COUNTIFS('BDRs (892)'!$C$2:$C$893,"BDR de ação",'BDRs (892)'!$E$2:$E$893,A14) -> 41 | C14: =SUMIFS('BDRs (892)'!$S$2:$S$893,'BDRs (892)'!$C$2:$C$893,"BDR de ação",'BDRs (892)'!$E$2:$E$893,A14) -> 1.6371e+08
A15: Bens de consumo não duráveis | B15: =COUNTIFS('BDRs (892)'!$C$2:$C$893,"BDR de ação",'BDRs (892)'!$E$2:$E$893,A15) -> 39 | C15: =SUMIFS('BDRs (892)'!$S$2:$S$893,'BDRs (892)'!$C$2:$C$893,"BDR de ação",'BDRs (892)'!$E$2:$E$893,A15) -> 2.1946989e+08
A16: Serviços ao consumidor | B16: =COUNTIFS('BDRs (892)'!$C$2:$C$893,"BDR de ação",'BDRs (892)'!$E$2:$E$893,A16) -> 33 | C16: =SUMIFS('BDRs (892)'!$S$2:$S$893,'BDRs (892)'!$C$2:$C$893,"BDR de ação",'BDRs (892)'!$E$2:$E$893,A16) -> 9165862.5
A17: Bens de produção | B17: =COUNTIFS('BDRs (892)'!$C$2:$C$893,"BDR de ação",'BDRs (892)'!$E$2:$E$893,A17) -> 31 | C17: =SUMIFS('BDRs (892)'!$S$2:$S$893,'BDRs (892)'!$C$2:$C$893,"BDR de ação",'BDRs (892)'!$E$2:$E$893,A17) -> 3197395.2
A18: Mineração e metais | B18: =COUNTIFS('BDRs (892)'!$C$2:$C$893,"BDR de ação",'BDRs (892)'!$E$2:$E$893,A18) -> 20 | C18: =SUMIFS('BDRs (892)'!$S$2:$S$893,'BDRs (892)'!$C$2:$C$893,"BDR de ação",'BDRs (892)'!$E$2:$E$893,A18) -> 1.6223797e+08
A19: Indústria de transformação | B19: =COUNTIFS('BDRs (892)'!$C$2:$C$893,"BDR de ação",'BDRs (892)'!$E$2:$E$893,A19) -> 19 | C19: =SUMIFS('BDRs (892)'!$S$2:$S$893,'BDRs (892)'!$C$2:$C$893,"BDR de ação",'BDRs (892)'!$E$2:$E$893,A19) -> 624403.95
A20: Utilidade pública | B20: =COUNTIFS('BDRs (892)'!$C$2:$C$893,"BDR de ação",'BDRs (892)'!$E$2:$E$893,A20) -> 19 | C20: =SUMIFS('BDRs (892)'!$S$2:$S$893,'BDRs (892)'!$C$2:$C$893,"BDR de ação",'BDRs (892)'!$E$2:$E$893,A20) -> 775770.82
A21: Transporte | B21: =COUNTIFS('BDRs (892)'!$C$2:$C$893,"BDR de ação",'BDRs (892)'!$E$2:$E$893,A21) -> 19 | C21: =SUMIFS('BDRs (892)'!$S$2:$S$893,'BDRs (892)'!$C$2:$C$893,"BDR de ação",'BDRs (892)'!$E$2:$E$893,A21) -> 5125837.3
... A28: Distribuição | B28: =COUNTIFS('BDRs (892)'!$C$2:$C$893,"BDR de ação",'BDRs (892)'!$E$2:$E$893,A28) -> 8 | C28: =SUMIFS('BDRs (892)'!$S$2:$S$893,'BDRs (892)'!$C$2:$C$893,"BDR de ação",'BDRs (892)'!$E$2:$E$893,A28) -> 271142.43
A29: Total | B29: =SUM(B10:B28) -> 668 | C29: =SUM(C10:C28) -> 1.6592861e+09
