Workbook

Sheet Leia-me
A1: Grupos (conglomerados) — Emissoras e Distribuidoras de Renda Fixa
A2: Gerado em 09/10/2026 no levantamento do escopo "Emissoras de Renda Fixa PrimeVest". Revisado no mesmo dia com as decisões abaixo.
A4: Fonte
A5: BCB — IF.data, cadastro (Olinda: IFDATA/IfDataCadastro), data-base 06/2026. Histórico das inativas: bases 12/2018, 12/2020, 12/2022 e 12/2024.
A6: Grupo = conglomerado prudencial do BCB (o mesmo critério do FGC).
A8: Decisões (09/10/2026)
A9: Todo conglomerado do BCB vira grupo, inclusive os de uma empresa só.
A10: Nome do grupo = coluna "Nome PrimeVest": a sugestão, sem curadoria. Origem "manual" = escolhida no levantamento (aceita pelo Guilherme); "automática" = nome do BCB sem siglas societárias.
A11: Empresas inativas são associadas ao grupo que tinham (aba "Inativas — grupo antigo"). Grupos que já não existem na base atual entram como "Extinto".
A12: Empresas só da CVM (securitizadoras, companhias de debênture) não têm grupo no BCB; podem ser associadas a um grupo por curadoria.
A13: Cooperativas de crédito não têm conglomerado prudencial no BCB (o agrupamento natural é o sistema: Sicoob, Sicredi, Unicred) — fora desta planilha.
A15: Colunas
... A17: "Qtde empresas" é fórmula (CONT.SE na aba Empresas). Situação (BCB): Ativa, Inativa, Liquidação extrajudicial, Liquidação ordinária, Falência.

Sheet Grupos
A1: Tipo | B1: Relevante RF | C1: Código grupo | D1: Nome BCB | E1: Nome PrimeVest | F1: Origem do nome | G1: CNPJ raiz líder | H1: Empresa líder | I1: Qtde empresas | J1: Empresas do grupo
A2: Várias empresas | B2: Sim | C2: C0080312 | D2: ABC-BRASIL - PRUDENCIAL | E2: ABC Brasil | F2: manual | G2: 28195667 | H2: BANCO ABC BRASIL S.A. | I2: =COUNTIF(Empresas!$A$2:$A$965,C2) -> 2 | J2: ABC BRASIL DISTRIBUIDORA DE TÍTULOS E VALORES MOBILIÁRIOS S.A.; BANCO ABC BRASIL S.A.
A3: Várias empresas | B3: Sim | C3: C0081579 | D3: BCO ABN AMRO CLEARING - PRUDENCIAL | E3: ABN AMRO | F3: manual | G3: 03532415 | H3: BANCO ABN AMRO CLEARING S.A. | I3: =COUNTIF(Empresas!$A$2:$A$965,C3) -> 2 | J3: ABN AMRO CLEARING CORRETORA DE TÍTULOS E VALORES MOBILIÁRIOS LTDA.; BANCO ABN AMRO CLEARING S.A.
A4: Várias empresas | B4: Sim | C4: C0083539 | D4: BANCO AFINZ BM - PRUDENCIAL | E4: Afinz | F4: manual | G4: 04814563 | H4: BANCO AFINZ S.A. - BANCO MÚLTIPLO | I4: =COUNTIF(Empresas!$A$2:$A$965,C4) -> 2 | J4: AFINZ INSTITUIÇÃO DE PAGAMENTO S.A.; BANCO AFINZ S.A. - BANCO MÚLTIPLO
A5: Várias empresas | B5: Sim | C5: C0083694 | D5: AGIBANK - PRUDENCIAL | E5: Agibank | F5: manual | G5: 10664513 | H5: BANCO AGIBANK S.A. | I5: =COUNTIF(Empresas!$A$2:$A$965,C5) -> 2 | J5: AGI FINANCEIRA S.A. - SOCIEDADE DE CRÉDITO, FINANCIAMENTO E INVESTIMENTO; BANCO AGIBANK S.A.
A6: Várias empresas | B6: Sim | C6: C0081256 | D6: ANDBANK - PRUDENCIAL | E6: Andbank | F6: manual | G6: 48795256 | H6: BANCO ANDBANK (BRASIL) S.A. | I6: =COUNTIF(Empresas!$A$2:$A$965,C6) -> 3 | J6: ANDBANK DISTRIBUIDORA DE TÍTULOS E VALORES MOBILIÁRIOS LTDA.; BANCO ANDBANK (BRASIL) S.A.; CREDITAS SOCIEDADE DE CRÉDITO DIRETO S.A.
A7: Várias empresas | B7: Sim | C7: C0085771 | D7: ASAAS GESTAO FINANCEIRA IP - PRUDENCIAL | E7: Asaas | F7: manual | G7: 19540550 | H7: ASAAS GESTÃO FINANCEIRA INSTITUIÇÃO DE PAGAMENTO S.A. | I7: =COUNTIF(Empresas!$A$2:$A$965,C7) -> 2 | J7: ASAAS GESTÃO FINANCEIRA INSTITUIÇÃO DE PAGAMENTO S.A.; ASAAS SOCIEDADE DE CRÉDITO, FINANCIAMENTO E INVESTIMENTO S.A.
A8: Várias empresas | B8: Sim | C8: C0081225 | D8: BANCO B3 - PRUDENCIAL | E8: B3 | F8: manual | G8: 00997185 | H8: BANCO B3 S.A. | I8: =COUNTIF(Empresas!$A$2:$A$965,C8) -> 2 | J8: B3 INSTITUICAO DE PAGAMENTO LTDA; BANCO B3 S.A.
A9: Várias empresas | B9: Sim | C9: C0080329 | D9: BB - PRUDENCIAL | E9: Banco do Brasil | F9: manual | G9: 00000000 | H9: BANCO DO BRASIL S.A. | I9: =COUNTIF(Empresas!$A$2:$A$965,C9) -> 7 | J9: BANCO DO BRASIL S.A.; BB ADMINISTRADORA DE CARTOES DE CREDITO S A; BB ADMINISTRADORA DE CONSORCIOS S.A.; BB GESTÃO DE RECURSOS - DISTRIBUIDORA DE TÍTULOS E VALORES MOBILIÁRIOS S.A.; BB-BANCO DE INVESTIMENTO S/A; BB-LEASING S/A ARRENDAMENTO MERCANTIL; BESC-DISTRIBUIDORA DE TITULOS E VALORES MOBILIARIOS SA-BESCVAL
A10: Várias empresas | B10: Sim | C10: C0080477 | D10: INDUSTRIAL DO BRASIL - PRUDENCIAL | E10: Banco Industrial | F10: manual | G10: 31895683 | H10: BANCO INDUSTRIAL DO BRASIL S.A. | I10: =COUNTIF(Empresas!$A$2:$A$965,C10) -> 2 | J10: BANCO INDUSTRIAL DO BRASIL S.A.; INDUSTRIAL DO BRASIL DISTRIBUIDORA DE TÍTULOS E VALORES MOBILIÁRIOS LTDA.
A11: Várias empresas | B11: Sim | C11: C0081634 | D11: BCO DO EST. DE SE S.A. - PRUDENCIAL | E11: Banese | F11: manual | G11: 13009717 | H11: BANCO DO ESTADO DE SERGIPE S.A. | I11: =COUNTIF(Empresas!$A$2:$A$965,C11) -> 2 | J11: BANCO DO ESTADO DE SERGIPE S.A.; MULVI INSTITUICAO DE PAGAMENTO S.A.
A12: Várias empresas | B12: Sim | C12: C0080147 | D12: BANESTES - PRUDENCIAL | E12: Banestes | F12: manual | G12: 28127603 | H12: BANESTES S.A. BANCO DO ESTADO DO ESPIRITO SANTO | I12: =COUNTIF(Empresas!$A$2:$A$965,C12) -> 2 | J12: BANESTES DISTRIBUIDORA DE TITULOS E VALORES MOBILIARIOS S/A; BANESTES S.A. BANCO DO ESTADO DO ESPIRITO SANTO
A13: Várias empresas | B13: Sim | C13: C0080556 | D13: BOFA MERRILL LYNCH - PRUDENCIAL | E13: Bank of America | F13: manual | G13: 62073200 | H13: BANK OF AMERICA MERRILL LYNCH BANCO MÚLTIPLO S.A. | I13: =COUNTIF(Empresas!$A$2:$A$965,C13) -> 2 | J13: BANK OF AMERICA MERRILL LYNCH BANCO MÚLTIPLO S.A.; MERRILL LYNCH S.A. CORRETORA DE TÍTULOS E VALORES MOBILIÁRIOS
... A109: Várias empresas | B109: Sim | C109: C0083584 | D109: ZEMA CFI - PRUDENCIAL | E109: Zema | F109: automática | G109: 05351887 | H109: ZEMA CRÉDITO, FINANCIAMENTO E INVESTIMENTO S/A | I109: =COUNTIF(Empresas!$A$2:$A$965,C109) -> 2 | J109: ZEMA ADMINISTRADORA DE CONSÓRCIO LTDA; ZEMA CRÉDITO, FINANCIAMENTO E INVESTIMENTO S/A
A110: Extinto | B110: Sim | C110: C0080367 | D110: BANCO MASTER (bases antigas) | E110: Banco Master | F110: manual | I110: =COUNTIF(Empresas!$A$2:$A$965,C110) -> 8 | J110: BANCO LETSBANK S.A. - EM LIQUIDAÇÃO EXTRAJUDICIAL; BANCO MASTER DE INVESTIMENTO S.A. - EM LIQUIDAÇÃO EXTRAJUDICIAL; BANCO MASTER MÚLTIPLO S.A. - EM LIQUIDAÇÃO EXTRAJUDICIAL; BANCO MASTER S/A - EM LIQUIDAÇÃO EXTRAJUDICIAL; BANCO PLENO S.A. - EM LIQUIDAÇÃO EXTRAJUDICIAL; MASTER S/A CORRETORA DE CÂMBIO, TÍTULOS E VALORES MOBILIÁRIOS - EM LIQUIDAÇÃO EXTRAJUDICIAL; PLENO DISTRIBUIDORA DE TÍTULOS E VALORES MOBILIÁRIOS S.A. - EM LIQUIDAÇÃO EXTRAJUDICIAL; WILL FINANCEIRA S.A. CRÉDITO, FINANCIAMENTO E INVESTIMENTO - EM LIQUIDAÇÃO EXTRAJUDICIAL
A111: Extinto | B111: Sim | C111: C0081005 | D111: DACASA FINANCEIRA (bases antigas) | E111: Dacasa Financeira | F111: manual | I111: =COUNTIF(Empresas!$A$2:$A$965,C111) -> 2 | J111: DACASA FINANCEIRA S/A - SOCIEDADE DE CRÉDITO, FINANCIAMENTO E INVESTIMENTO; UNILETRA CORRETORA DE CÂMBIO, TÍTULOS E VALORES MOBILIÁRIOS S.A.
A112: Uma empresa | B112: Sim | C112: C0085977 | D112: ACTIVTRADES CCTVM - PRUDENCIAL | E112: Activtrades | F112: automática | G112: 43050917 | H112: ACTIVTRADES CORRETORA DE CÂMBIO, TÍTULOS E VALORES MOBILIÁRIOS LTDA. | I112: =COUNTIF(Empresas!$A$2:$A$965,C112) -> 1 | J112: ACTIVTRADES CORRETORA DE CÂMBIO, TÍTULOS E VALORES MOBILIÁRIOS LTDA.
A113: Uma empresa | B113: Sim | C113: C0087243 | D113: ACTUAL DTVM - PRUDENCIAL | E113: Actual | F113: automática | G113: 44782130 | H113: ACTUAL DISTRIBUIDORA DE TÍTULOS E VALORES MOBILIÁRIOS S.A. | I113: =COUNTIF(Empresas!$A$2:$A$965,C113) -> 1 | J113: ACTUAL DISTRIBUIDORA DE TÍTULOS E VALORES MOBILIÁRIOS S.A.
A114: Uma empresa | B114: Sim | C114: C0083618 | D114: AGORACRED S/A SCFI - PRUDENCIAL | E114: Agoracred | F114: automática | G114: 36321990 | H114: AGORACRED S/A SOCIEDADE DE CRÉDITO, FINANCIAMENTO E INVESTIMENTO | I114: =COUNTIF(Empresas!$A$2:$A$965,C114) -> 1 | J114: AGORACRED S/A SOCIEDADE DE CRÉDITO, FINANCIAMENTO E INVESTIMENTO
A115: Uma empresa | B115: Sim | C115: C0085867 | D115: AGROLEND SCFI - PRUDENCIAL | E115: Agrolend | F115: automática | G115: 43774196 | H115: AGROLEND SOCIEDADE DE CREDITO, FINANCIAMENTO E INVESTIMENTO S.A. | I115: =COUNTIF(Empresas!$A$2:$A$965,C115) -> 1 | J115: AGROLEND SOCIEDADE DE CREDITO, FINANCIAMENTO E INVESTIMENTO S.A.
A116: Uma empresa | B116: Sim | C116: C0084734 | D116: AL5 S.A. SCFI - PRUDENCIAL | E116: Al5 | F116: automática | G116: 27214112 | H116: AL5 S.A. SOCIEDADE DE CRÉDITO, FINANCIAMENTO E INVESTIMENTO | I116: =COUNTIF(Empresas!$A$2:$A$965,C116) -> 1 | J116: AL5 S.A. SOCIEDADE DE CRÉDITO, FINANCIAMENTO E INVESTIMENTO
A117: Uma empresa | B117: Sim | C117: C0082516 | D117: AMARIL FRANKLIN CTV LTDA - PRUDENCIAL | E117: Amaril Franklin | F117: automática | G117: 17312661 | H117: AMARIL FRANKLIN CORRETORA DE TÍTULOS E VALORES LTDA | I117: =COUNTIF(Empresas!$A$2:$A$965,C117) -> 1 | J117: AMARIL FRANKLIN CORRETORA DE TÍTULOS E VALORES LTDA
A118: Uma empresa | B118: Sim | C118: C0088871 | D118: AMICORP DTVM - PRUDENCIAL | E118: Amicorp | F118: automática | G118: 54211458 | H118: AMICORP DISTRIBUIDORA DE TÍTULOS E VALORES MOBILIÁRIOS LTDA. | I118: =COUNTIF(Empresas!$A$2:$A$965,C118) -> 1 | J118: AMICORP DISTRIBUIDORA DE TÍTULOS E VALORES MOBILIÁRIOS LTDA.
A119: Uma empresa | B119: Sim | C119: C0086608 | D119: ASA SCFI - PRUDENCIAL | E119: ASA | F119: automática | G119: 48703388 | H119: ASA SOCIEDADE DE CRÉDITO FINANCIAMENTO E INVESTIMENTO S.A. | I119: =COUNTIF(Empresas!$A$2:$A$965,C119) -> 1 | J119: ASA SOCIEDADE DE CRÉDITO FINANCIAMENTO E INVESTIMENTO S.A.
A120: Uma empresa | B120: Sim | C120: C0082547 | D120: ATIVA S.A. CTCV - PRUDENCIAL | E120: Ativa Investimentos | F120: manual | G120: 33775974 | H120: ATIVA INVESTIMENTOS S.A. CORRETORA DE TÍTULOS, CÂMBIO E VALORES | I120: =COUNTIF(Empresas!$A$2:$A$965,C120) -> 1 | J120: ATIVA INVESTIMENTOS S.A. CORRETORA DE TÍTULOS, CÂMBIO E VALORES
A121: Uma empresa | B121: Sim | C121: C0084325 | D121: AZIMUT BRASIL DTVM - PRUDENCIAL | E121: Azimut Brasil | F121: automática | G121: 18684408 | H121: AZIMUT BRASIL DISTRIBUIDORA DE TÍTULOS E VALORES MOBILIÁRIOS LTDA | I121: =COUNTIF(Empresas!$A$2:$A$965,C121) -> 1 | J121: AZIMUT BRASIL DISTRIBUIDORA DE TÍTULOS E VALORES MOBILIÁRIOS LTDA
A122: Uma empresa | B122: Sim | C122: C0085719 | D122: AZUMI DTVM PRUDENCIAL | E122: Azumi | F122: automática | G122: 40434681 | H122: AZUMI DISTRIBUIDORA DE TÍTULOS E VALORES MOBILIÁRIOS LTDA. | I122: =COUNTIF(Empresas!$A$2:$A$965,C122) -> 1 | J122: AZUMI DISTRIBUIDORA DE TÍTULOS E VALORES MOBILIÁRIOS LTDA.
A123: Uma empresa | B123: Sim | C123: C0081201 | D123: BCO ARBI S.A. - PRUDENCIAL | E123: Banco Arbi | F123: automática | G123: 54403563 | H123: BANCO ARBI S.A. | I123: =COUNTIF(Empresas!$A$2:$A$965,C123) -> 1 | J123: BANCO ARBI S.A.
... A660: Uma empresa | B660: Não | C660: C0087638 | D660: ÓPERA SCD - PRUDENCIAL | E660: Ópera | F660: automática | G660: 55841657 | H660: ÓPERA SOCIEDADE DE CRÉDITO DIRETO S.A. | I660: =COUNTIF(Empresas!$A$2:$A$965,C660) -> 1 | J660: ÓPERA SOCIEDADE DE CRÉDITO DIRETO S.A.

Sheet Empresas
A1: Código grupo | B1: Grupo (Nome PrimeVest) | C1: CNPJ raiz | D1: Razão social | E1: Segmento | F1: Situação | G1: Líder do grupo | H1: Origem do vínculo
A2: C0087597 | B2: 3x | C2: 36010822 | D2: 3X INSTITUIÇÃO DE PAGAMENTO LTDA | E2: Instituição de Pagamento | F2: Ativa | G2: Sim | H2: BCB 06/2026
A3: C0088606 | B3: 8b Servicos Financeiros | C3: 55586562 | D3: 8B SERVICOS FINANCEIROS INSTITUICAO DE PAGAMENTO S/A | E3: Instituição de Pagamento | F3: Inativa | G3: Sim | H3: BCB 06/2026
A4: C0087793 | B4: 99Pay | C4: 24313102 | D4: 99PAY INSTITUICAO DE PAGAMENTO S.A. | E4: Instituição de Pagamento | F4: Ativa | G4: Sim | H4: BCB 06/2026
A5: C0087793 | B5: 99Pay | C5: 59379565 | D5: 99PAY SOCIEDADE DE CRÉDITO DIRETO S.A. | E5: Sociedade de Crédito Direto | F5: Ativa | H5: BCB 06/2026
A6: C0087504 | B6: A27 | C6: 35534511 | D6: A27 INSTITUICAO DE PAGAMENTOS S/A | E6: Instituição de Pagamento | F6: Ativa | G6: Sim | H6: BCB 06/2026
A7: C0086512 | B7: A55 | C7: 48756121 | D7: A55 SOCIEDADE DE CRÉDITO DIRETO S.A. | E7: Sociedade de Crédito Direto | F7: Ativa | G7: Sim | H7: BCB 06/2026
A8: C0080312 | B8: ABC Brasil | C8: 28195667 | D8: BANCO ABC BRASIL S.A. | E8: Banco Múltiplo | F8: Ativa | G8: Sim | H8: BCB 06/2026
A9: C0080312 | B9: ABC Brasil | C9: 33817677 | D9: ABC BRASIL DISTRIBUIDORA DE TÍTULOS E VALORES MOBILIÁRIOS S.A. | E9: Sociedade Distribuidora de TVM | F9: Ativa | H9: BCB 06/2026
A10: C0081579 | B10: ABN AMRO | C10: 03532415 | D10: BANCO ABN AMRO CLEARING S.A. | E10: Banco Múltiplo | F10: Ativa | G10: Sim | H10: BCB 06/2026
A11: C0081579 | B11: ABN AMRO | C11: 44527444 | D11: ABN AMRO CLEARING CORRETORA DE TÍTULOS E VALORES MOBILIÁRIOS LTDA. | E11: Sociedade Corretora de TVM | F11: Ativa | H11: BCB 06/2026
A12: C0087559 | B12: Accesstage | C12: 46410407 | D12: ACCESSTAGE INSTITUIÇÃO DE PAGAMENTO LTDA. | E12: Instituição de Pagamento | F12: Inativa | G12: Sim | H12: BCB 06/2026
A13: C0085331 | B13: Accredito | C13: 37715993 | D13: ACCREDITO - SOCIEDADE DE CRÉDITO DIRETO S.A. | E13: Sociedade de Crédito Direto | F13: Ativa | G13: Sim | H13: BCB 06/2026
A14: C0086093 | B14: ACG | C14: 10868663 | D14: ACG INSTITUIÇÃO DE PAGAMENTO S.A. | E14: Instituição de Pagamento | F14: Ativa | G14: Sim | H14: BCB 06/2026
A15: C0085977 | B15: Activtrades | C15: 43050917 | D15: ACTIVTRADES CORRETORA DE CÂMBIO, TÍTULOS E VALORES MOBILIÁRIOS LTDA. | E15: Sociedade Corretora de TVM | F15: Ativa | G15: Sim | H15: BCB 06/2026
A16: C0087243 | B16: Actual | C16: 44782130 | D16: ACTUAL DISTRIBUIDORA DE TÍTULOS E VALORES MOBILIÁRIOS S.A. | E16: Sociedade Distribuidora de TVM | F16: Ativa | G16: Sim | H16: BCB 06/2026
A17: C0087401 | B17: Adyen do Brasil | C17: 14796606 | D17: ADYEN DO BRASIL INSTITUICAO DE PAGAMENTO LTDA. | E17: Instituição de Pagamento | F17: Ativa | G17: Sim | H17: BCB 06/2026
A18: C0081153 | B18: AF Desenvolve SP | C18: 10663610 | D18: DESENVOLVE SP - AGÊNCIA DE FOMENTO DO ESTADO DE SÃO PAULO S.A. | E18: Agência de Fomento | F18: Ativa | G18: Sim | H18: BCB 06/2026
A19: C0081074 | B19: AF do Estado de SC | C19: 82937293 | D19: AGÊNCIA DE FOMENTO DO ESTADO DE SANTA CATARINA S.A.-BADESC | E19: Agência de Fomento | F19: Ativa | G19: Sim | H19: BCB 06/2026
A20: C0081177 | B20: AF Estado de Pernambuco | C20: 13178690 | D20: AGÊNCIA DE FOMENTO DO ESTADO DE PERNAMBUCO S.A. | E20: Agência de Fomento | F20: Ativa | G20: Sim | H20: BCB 06/2026
A21: C0081115 | B21: AF Paraná | C21: 03584906 | D21: AGÊNCIA DE FOMENTO DO PARANÁ S.A. | E21: Agência de Fomento | F21: Ativa | G21: Sim | H21: BCB 06/2026
A22: C0081081 | B22: Afal | C22: 10769660 | D22: AGÊNCIA DE FOMENTO DE ALAGOAS S.A. | E22: Agência de Fomento | F22: Ativa | G22: Sim | H22: BCB 06/2026
A23: C0081108 | B23: Afeam | C23: 03183937 | D23: AGÊNCIA DE FOMENTO DO ESTADO DO AMAZONAS S.A. - AFEAM | E23: Agência de Fomento | F23: Ativa | G23: Sim | H23: BCB 06/2026
A24: C0083539 | B24: Afinz | C24: 04814563 | D24: BANCO AFINZ S.A. - BANCO MÚLTIPLO | E24: Banco Múltiplo | F24: Ativa | G24: Sim | H24: BCB 06/2026
A25: C0083539 | B25: Afinz | C25: 60114865 | D25: AFINZ INSTITUIÇÃO DE PAGAMENTO S.A. | E25: Instituição de Pagamento | F25: Ativa | H25: BCB 06/2026
A26: C0081043 | B26: Agencia de Fomento do RN | C26: 03848103 | D26: AGENCIA DE FOMENTO DO RIO GRANDE DO NORTE S.A. | E26: Agência de Fomento | F26: Ativa | G26: Sim | H26: BCB 06/2026
A27: C0081139 | B27: Agencia Fomento Est RJ | C27: 05940203 | D27: AGENCIA DE FOMENTO DO ESTADO DO RIO DE JANEIRO S.A. | E27: Agência de Fomento | F27: Ativa | G27: Sim | H27: BCB 06/2026
A28: C0081050 | B28: Agencia Fomento Goias | C28: 03918382 | D28: AGENCIA DE FOMENTO DE GOIAS S/A | E28: Agência de Fomento | F28: Ativa | G28: Sim | H28: BCB 06/2026
A29: C0081029 | B29: Agencia Fomento RS Badesul | C29: 02885855 | D29: BADESUL DESENVOLVIMENTO S.A - AGÊNCIA DE FOMENTO/RS | E29: Agência de Fomento | F29: Ativa | G29: Sim | H29: BCB 06/2026
A30: C0083694 | B30: Agibank | C30: 10664513 | D30: BANCO AGIBANK S.A. | E30: Banco Comercial | F30: Ativa | G30: Sim | H30: BCB 06/2026
A31: C0083694 | B31: Agibank | C31: 13660104 | D31: AGI FINANCEIRA S.A. - SOCIEDADE DE CRÉDITO, FINANCIAMENTO E INVESTIMENTO | E31: Sociedade de Crédito, Financiamento e Investimento | F31: Ativa | H31: BCB 06/2026
A32: C0082035 | B32: AGK | C32: 00250699 | D32: AGK CORRETORA DE CAMBIO S.A. | E32: Sociedade Corretora de Câmbio | F32: Ativa | G32: Sim | H32: BCB 06/2026
A33: C0083618 | B33: Agoracred | C33: 36321990 | D33: AGORACRED S/A SOCIEDADE DE CRÉDITO, FINANCIAMENTO E INVESTIMENTO | E33: Sociedade de Crédito, Financiamento e Investimento | F33: Ativa | G33: Sim | H33: BCB 06/2026
A34: C0085867 | B34: Agrolend | C34: 43774196 | D34: AGROLEND SOCIEDADE DE CREDITO, FINANCIAMENTO E INVESTIMENTO S.A. | E34: Sociedade de Crédito, Financiamento e Investimento | F34: Ativa | G34: Sim | H34: BCB 06/2026
A35: C0081146 | B35: Agência de Fomento Mato Grosso | C35: 06284531 | D35: AGÊNCIA DE FOMENTO DO ESTADO DE MATO GROSSO S/A - DESENVOLVE MT | E35: Agência de Fomento | F35: Ativa | G35: Sim | H35: BCB 06/2026
A36: C0081098 | B36: Agência Fomento Amapa | C36: 02929977 | D36: AGENCIA DE FOMENTO DO AMAPA S.A. | E36: Agência de Fomento | F36: Ativa | G36: Sim | H36: BCB 06/2026
A37: C0081036 | B37: Agência Fomento Estado de Roraima | C37: 03058464 | D37: AGENCIA DE FOMENTO DO ESTADO DE RORAIMA S/A | E37: Agência de Fomento | F37: Ativa | G37: Sim | H37: BCB 06/2026
A38: C0081122 | B38: Agência Fomento Estado do Tocantins | C38: 05474540 | D38: AGÊNCIA DE FOMENTO DO ESTADO DO TOCANTINS S.A. | E38: Agência de Fomento | F38: Ativa | G38: Sim | H38: BCB 06/2026
A39: C0084734 | B39: Al5 | C39: 27214112 | D39: AL5 S.A. SOCIEDADE DE CRÉDITO, FINANCIAMENTO E INVESTIMENTO | E39: Sociedade de Crédito, Financiamento e Investimento | F39: Ativa | G39: Sim | H39: BCB 06/2026
A40: C0085379 | B40: Alesta Sociedade de Credito Direto | C40: 38316293 | D40: ALESTA SOCIEDADE DE CREDITO DIRETO S.A. | E40: Sociedade de Crédito Direto | F40: Ativa | G40: Sim | H40: BCB 06/2026
A41: C0087085 | B41: ALL IN Cred | C41: 51414521 | D41: ALL IN CRED SOCIEDADE DE CREDITO DIRETO S.A. | E41: Sociedade de Crédito Direto | F41: Ativa | G41: Sim | H41: BCB 06/2026
A42: C0082516 | B42: Amaril Franklin | C42: 17312661 | D42: AMARIL FRANKLIN CORRETORA DE TÍTULOS E VALORES LTDA | E42: Sociedade Corretora de TVM | F42: Ativa | G42: Sim | H42: BCB 06/2026
A43: C0088871 | B43: Amicorp | C43: 54211458 | D43: AMICORP DISTRIBUIDORA DE TÍTULOS E VALORES MOBILIÁRIOS LTDA. | E43: Sociedade Distribuidora de TVM | F43: Inativa | G43: Sim | H43: BCB 06/2026
A44: C0081256 | B44: Andbank | C44: 48795256 | D44: BANCO ANDBANK (BRASIL) S.A. | E44: Banco Múltiplo | F44: Ativa | G44: Sim | H44: BCB 06/2026
A45: C0081256 | B45: Andbank | C45: 67600379 | D45: ANDBANK DISTRIBUIDORA DE TÍTULOS E VALORES MOBILIÁRIOS LTDA. | E45: Sociedade Distribuidora de TVM | F45: Ativa | H45: BCB 06/2026
A46: C0081256 | B46: Andbank | C46: 32997490 | D46: CREDITAS SOCIEDADE DE CRÉDITO DIRETO S.A. | E46: Sociedade de Crédito Direto | F46: Ativa | H46: BCB 06/2026
A47: C0081184 | B47: APE Poupex | C47: 00655522 | D47: ASSOCIACAO DE POUPANCA E EMPRESTIMO - POUPEX | E47: Associação de Poupança e Empréstimo | F47: Ativa | G47: Sim | H47: BCB 06/2026
A48: C0087573 | B48: Aproms Net | C48: 37168145 | D48: APROMS NET INSTITUICAO DE PAGAMENTO LTDA. | E48: Instituição de Pagamento | F48: Ativa | G48: Sim | H48: BCB 06/2026
A49: C0088565 | B49: Apusdigital | C49: 57654096 | D49: APUSDIGITAL INSTITUICAO DE PAGAMENTO LTDA | E49: Instituição de Pagamento | F49: Ativa | G49: Sim | H49: BCB 06/2026
A50: C0082066 | B50: ARC Corretora Cambio | C50: 04684647 | D50: ARC CORRETORA DE CAMBIO, ASSOCIADOS GOUVEIA, CAMPEDELLI S.A. | E50: Sociedade Corretora de Câmbio | F50: Ativa | G50: Sim | H50: BCB 06/2026
A51: C0085661 | B51: Artta | C51: 42259084 | D51: ARTTA SOCIEDADE DE CRÉDITO DIRETO S.A | E51: Sociedade de Crédito Direto | F51: Ativa | G51: Sim | H51: BCB 06/2026
A52: C0086608 | B52: ASA | C52: 48703388 | D52: ASA SOCIEDADE DE CRÉDITO FINANCIAMENTO E INVESTIMENTO S.A. | E52: Sociedade de Crédito, Financiamento e Investimento | F52: Ativa | G52: Sim | H52: BCB 06/2026
A53: C0085771 | B53: Asaas | C53: 19540550 | D53: ASAAS GESTÃO FINANCEIRA INSTITUIÇÃO DE PAGAMENTO S.A. | E53: Instituição de Pagamento | F53: Ativa | G53: Sim | H53: BCB 06/2026
A54: C0085771 | B54: Asaas | C54: 48786608 | D54: ASAAS SOCIEDADE DE CRÉDITO, FINANCIAMENTO E INVESTIMENTO S.A. | E54: Sociedade de Crédito, Financiamento e Investimento | F54: Ativa | H54: BCB 06/2026
A55: C0083058 | B55: Aspenfin-Br | C55: 05289612 | D55: ASPENFIN-BR - SOCIEDADE DE CRÉDITO AO MICROEMPREENDEDOR E A EMPRESA DE PEQUENO PORTE LTDA. | E55: Sociedade de Crédito ao Microempreendedor | F55: Ativa | G55: Sim | H55: BCB 06/2026
A56: C0088620 | B56: Astra | C56: 56913800 | D56: ASTRA INSTITUIÇÃO DE PAGAMENTO LTDA. | E56: Instituição de Pagamento | F56: Inativa | G56: Sim | H56: BCB 06/2026
A57: C0088156 | B57: Astro | C57: 34006497 | D57: ASTRO INSTITUICAO DE PAGAMENTO LTDA. | E57: Instituição de Pagamento | F57: Ativa | G57: Sim | H57: BCB 06/2026
A58: C0085915 | B58: ATF | C58: 44728700 | D58: ATF SOCIEDADE DE CRÉDITO DIRETO S.A. | E58: Sociedade de Crédito Direto | F58: Ativa | G58: Sim | H58: BCB 06/2026
A59: C0085946 | B59: Aticca | C59: 44478623 | D59: ATICCA - SOCIEDADE DE CRÉDITO DIRETO S.A. | E59: Sociedade de Crédito Direto | F59: Ativa | G59: Sim | H59: BCB 06/2026
A60: C0082547 | B60: Ativa Investimentos | C60: 33775974 | D60: ATIVA INVESTIMENTOS S.A. CORRETORA DE TÍTULOS, CÂMBIO E VALORES | E60: Sociedade Corretora de TVM | F60: Ativa | G60: Sim | H60: BCB 06/2026
A61: C0083034 | B61: Atlanta | C61: 04772908 | D61: ATLANTA SOCIEDADE DE CRÉDITO AO MICROEMPREENDEDOR LTDA | E61: Sociedade de Crédito ao Microempreendedor | F61: Ativa | G61: Sim | H61: BCB 06/2026
A62: C0087449 | B62: Attrus | C62: 10789035 | D62: ATTRUS INSTITUIÇÃO DE PAGAMENTO S/A | E62: Instituição de Pagamento | F62: Ativa | G62: Sim | H62: BCB 06/2026
A63: C0087858 | B63: Atual | C63: 44323831 | D63: ATUAL SOCIEDADE CORRETORA DE CÂMBIO LTDA | E63: Sociedade Corretora de Câmbio | F63: Ativa | G63: Sim | H63: BCB 06/2026
A64: C0087212 | B64: Avancard Prover | C64: 20308187 | D64: AVANCARD PROVER INSTITUIÇÃO DE PAGAMENTO LTDA | E64: Instituição de Pagamento | F64: Ativa | G64: Sim | H64: BCB 06/2026
A65: C0087212 | B65: Avancard Prover | C65: 50032584 | D65: LOAN BRASIL SOCIEDADE DE CRÉDITO DIRETO S.A. | E65: Sociedade de Crédito Direto | F65: Ativa | H65: BCB 06/2026
A66: C0082042 | B66: Avipam | C66: 03443143 | D66: AVIPAM CORRETORA DE CAMBIO LTDA | E66: Sociedade Corretora de Câmbio | F66: Ativa | G66: Sim | H66: BCB 06/2026
A67: C0084590 | B67: AVS Corretora de Câmbio | C67: 25280945 | D67: AVS CORRETORA DE CÂMBIO LTDA. | E67: Sociedade Corretora de Câmbio | F67: Ativa | G67: Sim | H67: BCB 06/2026
A68: C0088242 | B68: AWX Brasil | C68: 52076716 | D68: AWX BRASIL INSTITUICAO DE PAGAMENTO LTDA | E68: Instituição de Pagamento | F68: Ativa | G68: Sim | H68: BCB 06/2026
A69: C0084325 | B69: Azimut Brasil | C69: 18684408 | D69: AZIMUT BRASIL DISTRIBUIDORA DE TÍTULOS E VALORES MOBILIÁRIOS LTDA | E69: Sociedade Distribuidora de TVM | F69: Ativa | G69: Sim | H69: BCB 06/2026
A70: C0085719 | B70: Azumi | C70: 40434681 | D70: AZUMI DISTRIBUIDORA DE TÍTULOS E VALORES MOBILIÁRIOS LTDA. | E70: Sociedade Distribuidora de TVM | F70: Ativa | G70: Sim | H70: BCB 06/2026
A71: C0081225 | B71: B3 | C71: 00997185 | D71: BANCO B3 S.A. | E71: Banco Comercial | F71: Ativa | G71: Sim | H71: BCB 06/2026
A72: C0081225 | B72: B3 | C72: 47825528 | D72: B3 INSTITUICAO DE PAGAMENTO LTDA | E72: Instituição de Pagamento | F72: Ativa | H72: BCB 06/2026
A73: C0086691 | B73: Bamaq Capital | C73: 48528314 | D73: BAMAQ CAPITAL - SOCIEDADE DE CRÉDITO DIRETO S/A | E73: Sociedade de Crédito Direto | F73: Ativa | G73: Sim | H73: BCB 06/2026
A74: C0081201 | B74: Banco Arbi | C74: 54403563 | D74: BANCO ARBI S.A. | E74: Banco Comercial | F74: Ativa | G74: Sim | H74: BCB 06/2026
A75: C0081414 | B75: Banco Cargill | C75: 03609817 | D75: BANCO CARGILL S.A. | E75: Banco Múltiplo | F75: Ativa | G75: Sim | H75: BCB 06/2026
A76: C0081397 | B76: Banco Caterpillar | C76: 02658435 | D76: BANCO CATERPILLAR S.A. | E76: Banco Múltiplo | F76: Ativa | G76: Sim | H76: BCB 06/2026
A77: C0081469 | B77: Banco Cedula | C77: 33132044 | D77: BANCO CEDULA S.A. | E77: Banco Múltiplo | F77: Ativa | G77: Sim | H77: BCB 06/2026
A78: C0081665 | B78: Banco Classico | C78: 31597552 | D78: BANCO CLASSICO S.A. | E78: Banco Múltiplo | F78: Ativa | G78: Sim | H78: BCB 06/2026
A79: C0081407 | B79: Banco CNH Industrial Capital | C79: 02992446 | D79: BANCO CNH INDUSTRIAL CAPITAL S.A. | E79: Banco Múltiplo | F79: Ativa | G79: Sim | H79: BCB 06/2026
A80: C0081610 | B80: Banco CSF | C80: 08357240 | D80: BANCO CSF S.A. | E80: Banco Múltiplo | F80: Ativa | G80: Sim | H80: BCB 06/2026
A81: C0081249 | B81: Banco da Amazonia | C81: 04902979 | D81: BANCO DA AMAZONIA S.A. | E81: Banco Comercial | F81: Ativa | G81: Sim | H81: BCB 06/2026
A82: C0081421 | B82: Banco de Lage Landen Brasil | C82: 05040481 | D82: BANCO DE LAGE LANDEN BRASIL S.A. | E82: Banco Múltiplo | F82: Ativa | G82: Sim | H82: BCB 06/2026
A83: C0081328 | B83: Banco Des. de MG | C83: 38486817 | D83: BANCO DE DESENVOLVIMENTO DE MINAS GERAIS S.A.-BDMG | E83: Banco de Desenvolvimento | F83: Ativa | G83: Sim | H83: BCB 06/2026
A84: C0081304 | B84: Banco Des. do ES | C84: 28145829 | D84: BANCO DE DESENVOLVIMENTO DO ESPIRITO SANTO S.A. | E84: Banco de Desenvolvimento | F84: Ativa | G84: Sim | H84: BCB 06/2026
... A86: C0080329 | B86: Banco do Brasil | C86: 00000000 | D86: BANCO DO BRASIL S.A. | E86: Banco do Brasil - Banco Múltiplo | F86: Ativa | G86: Sim | H86: BCB 06/2026
A87: C0080329 | B87: Banco do Brasil | C87: 31591399 | D87: BB ADMINISTRADORA DE CARTOES DE CREDITO S A | E87: Instituição de Pagamento não sujeita a autorização pelo BCB | F87: Ativa | H87: BCB 06/2026
A88: C0080329 | B88: Banco do Brasil | C88: 06043050 | D88: BB ADMINISTRADORA DE CONSORCIOS S.A. | E88: Administradora de Consórcio | F88: Ativa | H88: BCB 06/2026
A89: C0080329 | B89: Banco do Brasil | C89: 30822936 | D89: BB GESTÃO DE RECURSOS - DISTRIBUIDORA DE TÍTULOS E VALORES MOBILIÁRIOS S.A. | E89: Sociedade Distribuidora de TVM | F89: Ativa | H89: BCB 06/2026
A90: C0080329 | B90: Banco do Brasil | C90: 24933830 | D90: BB-BANCO DE INVESTIMENTO S/A | E90: Banco de Investimento | F90: Ativa | H90: BCB 06/2026
A91: C0080329 | B91: Banco do Brasil | C91: 31546476 | D91: BB-LEASING S/A ARRENDAMENTO MERCANTIL | E91: Sociedade de Arrendamento Mercantil | F91: Ativa | H91: BCB 06/2026
A92: C0080329 | B92: Banco do Brasil | C92: 82518523 | D92: BESC-DISTRIBUIDORA DE TITULOS E VALORES MOBILIARIOS SA-BESCVAL | E92: Sociedade Distribuidora de TVM | F92: Inativa | H92: Histórico 12/2020
A93: C0081586 | B93: Banco do Est. do PA | C93: 04913711 | D93: BANCO DO ESTADO DO PARÁ S.A. | E93: Banco Múltiplo | F93: Ativa | G93: Sim | H93: BCB 06/2026
A94: C0081593 | B94: Banco do Nordeste do Brasil | C94: 07237373 | D94: BANCO DO NORDESTE DO BRASIL S.A. | E94: Banco Múltiplo | F94: Ativa | G94: Sim | H94: BCB 06/2026
A95: C0081483 | B95: Banco Fibra | C95: 58616418 | D95: BANCO FIBRA S.A. | E95: Banco Múltiplo | F95: Ativa | G95: Sim | H95: BCB 06/2026
A96: C0081672 | B96: Banco Guanabara | C96: 31880826 | D96: BANCO GUANABARA S.A. | E96: Banco Múltiplo | F96: Ativa | G96: Sim | H96: BCB 06/2026
A97: C0084741 | B97: Banco Hsbc | C97: 53518684 | D97: BANCO HSBC S.A. | E97: Banco Múltiplo | F97: Ativa | G97: Sim | H97: BCB 06/2026
A98: C0081689 | B98: Banco IBM | C98: 34270520 | D98: BANCO IBM S.A. | E98: Banco Múltiplo | F98: Ativa | G98: Sim | H98: BCB 06/2026
A99: C0081335 | B99: Banco Inbursa | C99: 04866275 | D99: BANCO INBURSA S.A. | E99: Banco Múltiplo | F99: Ativa | G99: Sim | H99: BCB 06/2026
A100: C0081342 | B100: Banco Induscred de Investim | C100: 33588252 | D100: BANCO INDUSCRED DE INVESTIMENTO S.A. | E100: Banco de Investimento | F100: Ativa | G100: Sim | H100: BCB 06/2026
A101: C0080477 | B101: Banco Industrial | C101: 31895683 | D101: BANCO INDUSTRIAL DO BRASIL S.A. | E101: Banco Múltiplo | F101: Ativa | G101: Sim | H101: BCB 06/2026
...

Sheet Inativas — grupo antigo
A1: CNPJ raiz | B1: Razão social | C1: Segmento | D1: Situação hoje | E1: Última base com grupo | F1: Código grupo | G1: Grupo associado (Nome PrimeVest) | H1: Grupo ainda existe?
A2: 82518523 | B2: BESC-DISTRIBUIDORA DE TITULOS E VALORES MOBILIARIOS SA-BESCVAL | C2: Sociedade Distribuidora de TVM | D2: Inativa | E2: 12/2020 | F2: C0080329 | G2: Banco do Brasil | H2: Sim
A3: 58497702 | B3: BANCO LETSBANK S.A. - EM LIQUIDAÇÃO EXTRAJUDICIAL | C3: Banco Múltiplo | D3: Liquidação extrajudicial | E3: 12/2024 | F3: C0080367 | G3: Banco Master | H3: Não (extinto)
A4: 09526594 | B4: BANCO MASTER DE INVESTIMENTO S.A. - EM LIQUIDAÇÃO EXTRAJUDICIAL | C4: Banco de Investimento | D4: Liquidação extrajudicial | E4: 12/2024 | F4: C0080367 | G4: Banco Master | H4: Não (extinto)
A5: 33884941 | B5: BANCO MASTER MÚLTIPLO S.A. - EM LIQUIDAÇÃO EXTRAJUDICIAL | C5: Banco Múltiplo | D5: Liquidação extrajudicial | E5: 12/2024 | F5: C0080367 | G5: Banco Master | H5: Não (extinto)
A6: 33923798 | B6: BANCO MASTER S/A - EM LIQUIDAÇÃO EXTRAJUDICIAL | C6: Banco Comercial | D6: Liquidação extrajudicial | E6: 12/2024 | F6: C0080367 | G6: Banco Master | H6: Não (extinto)
A7: 61024352 | B7: BANCO PLENO S.A. - EM LIQUIDAÇÃO EXTRAJUDICIAL | C7: Banco Múltiplo | D7: Liquidação extrajudicial | E7: 12/2024 | F7: C0080367 | G7: Banco Master | H7: Não (extinto)
A8: 33886862 | B8: MASTER S/A CORRETORA DE CÂMBIO, TÍTULOS E VALORES MOBILIÁRIOS - EM LIQUIDAÇÃO EXTRAJUDICIAL | C8: Sociedade Corretora de TVM | D8: Liquidação extrajudicial | E8: 12/2024 | F8: C0080367 | G8: Banco Master | H8: Não (extinto)
A9: 02927433 | B9: PLENO DISTRIBUIDORA DE TÍTULOS E VALORES MOBILIÁRIOS S.A. - EM LIQUIDAÇÃO EXTRAJUDICIAL | C9: Sociedade Distribuidora de TVM | D9: Liquidação extrajudicial | E9: 12/2024 | F9: C0080367 | G9: Banco Master | H9: Não (extinto)
A10: 23862762 | B10: WILL FINANCEIRA S.A. CRÉDITO, FINANCIAMENTO E INVESTIMENTO - EM LIQUIDAÇÃO EXTRAJUDICIAL | C10: Sociedade de Crédito, Financiamento e Investimento | D10: Liquidação extrajudicial | E10: 12/2024 | F10: C0080367 | G10: Banco Master | H10: Não (extinto)
A11: 00558456 | B11: BANCO CETELEM S.A. | C11: Banco Múltiplo | D11: Inativa | E11: 12/2022 | F11: C0080673 | G11: BNP Paribas | H11: Sim
A12: 33870163 | B12: BANCO ALVORADA S.A. | C12: Banco Múltiplo | D12: Inativa | E12: 12/2018 | F12: C0080075 | G12: Bradesco | H12: Sim
... A33: 30723886 | B33: BANCO MODAL S.A. | C33: Banco Múltiplo | D33: Inativa | E33: 12/2024 | F33: C0082475 | G33: XP | H33: Sim
