Workbook

Sheet Leia-me
A1: Criptomoedas — levantamento CoinGecko
A3: Fonte | B3: CoinGecko API pública (sem chave) — /coins/markets (top 250 por valor de mercado) e /coins/markets?category=… para as categorias
A4: Coletado em | B4: 24/09/2026
A5: Sem cotação | B5: Nenhum preço foi gravado. O rank é só referência de relevância
A6: Universo | B6: Top 250 por valor de mercado → 227 entram + 23 excluídos (aba "Excluídos")
A7: Excluídos | B7: Derivativos (stablecoin com rendimento, token de ponte), fundos e títulos tokenizados (BUIDL, USYC, CLOs…), ação tokenizada e 2 com símbolo em ideogramas
A8: Ticker | B8: Símbolo da moeda em maiúsculas (BTC, ETH). Nenhum colide com tickers do catálogo (ações, FIIs, ETFs, BDRs, renda fixa)
A9: Categoria (mesma regra dos ETFs) | B9: description = tema · name = tema em MAIÚSCULAS sem acento · asset_type = CRIPTO · segment = categoria da CoinGecko que definiu o tema (inglês, traduzir na execução) ou Indefinido
A10: Prioridade do tema | B10: Uma moeda costuma estar em várias categorias da CoinGecko; vale a primeira desta lista: Stablecoins › Metais preciosos tokenizados › Tokens de corretora › Memecoins › Privacidade › Layer 2 › Layer 1 › Oráculos › Inteligência artificial › Ativos do mundo real (RWA) › DeFi › Games › Pagamentos › Outros
A11: Ajustes manuais | B11: KAG (Kinesis Silver) vai para Metais preciosos tokenizados; o tema "Ouro tokenizado" virou "Metais preciosos tokenizados"; SPX6900 entra (a CoinGecko o marca como token de ponte porque existe em várias redes, mas é a própria moeda)
A12: Id CoinGecko | B12: É o identificador que a API de preço usa (bitcoin, ethereum). Precisa ser gravado junto do ativo — hoje o CoinGeckoClient tem um mapa fixo de 14 moedas
A14: Resumo por categoria
A15: description | B15: Qtd.
A16: Layer 1 | B16: =COUNTIF('Criptos (227)'!$E$2:$E$228,A16) -> 52
A17: Stablecoins | B17: =COUNTIF('Criptos (227)'!$E$2:$E$228,A17) -> 34
A18: Tokens de corretora | B18: =COUNTIF('Criptos (227)'!$E$2:$E$228,A18) -> 30
A19: Outros | B19: =COUNTIF('Criptos (227)'!$E$2:$E$228,A19) -> 30
A20: Memecoins | B20: =COUNTIF('Criptos (227)'!$E$2:$E$228,A20) -> 20
A21: DeFi | B21: =COUNTIF('Criptos (227)'!$E$2:$E$228,A21) -> 19
A22: Inteligência artificial | B22: =COUNTIF('Criptos (227)'!$E$2:$E$228,A22) -> 14
A23: Layer 2 | B23: =COUNTIF('Criptos (227)'!$E$2:$E$228,A23) -> 8
A24: Ativos do mundo real (RWA) | B24: =COUNTIF('Criptos (227)'!$E$2:$E$228,A24) -> 5
A25: Games | B25: =COUNTIF('Criptos (227)'!$E$2:$E$228,A25) -> 5
A26: Metais preciosos tokenizados | B26: =COUNTIF('Criptos (227)'!$E$2:$E$228,A26) -> 4
A27: Privacidade | B27: =COUNTIF('Criptos (227)'!$E$2:$E$228,A27) -> 3
... A29: Pagamentos | B29: =COUNTIF('Criptos (227)'!$E$2:$E$228,A29) -> 1
A30: Total | B30: =SUM(B16:B29) -> 227

Sheet Criptos (227)
A1: Rank (valor de mercado) | B1: Ticker (símbolo) | C1: Nome | D1: Id CoinGecko | E1: Categoria — description | F1: Categoria — name | G1: Categoria — segment | H1: Logo (URL) | I1: Página CoinGecko
A2: 1 | B2: BTC | C2: Bitcoin | D2: bitcoin | E2: Layer 1 | F2: LAYER_1 | G2: Layer 1 (L1) | H2: https://coin-images.coingecko.com/coins/images/1/large/bitcoin.png?1696501400 | I2: https://www.coingecko.com/pt/moedas/bitcoin
A3: 2 | B3: ETH | C3: Ethereum | D3: ethereum | E3: Layer 1 | F3: LAYER_1 | G3: Layer 1 (L1) | H3: https://coin-images.coingecko.com/coins/images/279/large/ethereum.png?1696501628 | I3: https://www.coingecko.com/pt/moedas/ethereum
A4: 3 | B4: USDT | C4: Tether | D4: tether | E4: Stablecoins | F4: STABLECOINS | G4: Stablecoins | H4: https://coin-images.coingecko.com/coins/images/325/large/Tether.png?1696501661 | I4: https://www.coingecko.com/pt/moedas/tether
A5: 4 | B5: BNB | C5: BNB | D5: binancecoin | E5: Tokens de corretora | F5: TOKENS_DE_CORRETORA | G5: Exchange-based Tokens | H5: https://coin-images.coingecko.com/coins/images/825/large/bnb-icon2_2x.png?1696501970 | I5: https://www.coingecko.com/pt/moedas/binancecoin
A6: 5 | B6: XRP | C6: XRP | D6: ripple | E6: Layer 1 | F6: LAYER_1 | G6: Layer 1 (L1) | H6: https://coin-images.coingecko.com/coins/images/44/large/xrp-symbol-white-128.png?1696501442 | I6: https://www.coingecko.com/pt/moedas/ripple
A7: 6 | B7: USDC | C7: USDC | D7: usd-coin | E7: Stablecoins | F7: STABLECOINS | G7: Stablecoins | H7: https://coin-images.coingecko.com/coins/images/6319/large/USDC.png?1769615602 | I7: https://www.coingecko.com/pt/moedas/usd-coin
A8: 7 | B8: SOL | C8: Solana | D8: solana | E8: Layer 1 | F8: LAYER_1 | G8: Layer 1 (L1) | H8: https://coin-images.coingecko.com/coins/images/4128/large/solana.png?1718769756 | I8: https://www.coingecko.com/pt/moedas/solana
A9: 8 | B9: TRX | C9: TRON | D9: tron | E9: Layer 1 | F9: LAYER_1 | G9: Layer 1 (L1) | H9: https://coin-images.coingecko.com/coins/images/1094/large/photo_2026-04-13_09-59-16.png?1776048311 | I9: https://www.coingecko.com/pt/moedas/tron
A10: 9 | B10: ZEC | C10: Zcash | D10: zcash | E10: Privacidade | F10: PRIVACIDADE | G10: Privacy Coins | H10: https://coin-images.coingecko.com/coins/images/486/large/Brandmark-Yellow_%281%29.png?1785810558 | I10: https://www.coingecko.com/pt/moedas/zcash
A11: 11 | B11: HYPE | C11: Hyperliquid | D11: hyperliquid | E11: Tokens de corretora | F11: TOKENS_DE_CORRETORA | G11: Exchange-based Tokens | H11: https://coin-images.coingecko.com/coins/images/50882/large/hyperliquid.jpg?1729431300 | I11: https://www.coingecko.com/pt/moedas/hyperliquid
A12: 12 | B12: DOGE | C12: Dogecoin | D12: dogecoin | E12: Memecoins | F12: MEMECOINS | G12: Meme | H12: https://coin-images.coingecko.com/coins/images/5/large/dogecoin.png?1696501409 | I12: https://www.coingecko.com/pt/moedas/dogecoin
A13: 13 | B13: XMR | C13: Monero | D13: monero | E13: Privacidade | F13: PRIVACIDADE | G13: Privacy Coins | H13: https://coin-images.coingecko.com/coins/images/69/large/monero_logo.png?1696501460 | I13: https://www.coingecko.com/pt/moedas/monero
... A228: 250 | B228: GLM | C228: Golem | D228: golem | E228: Inteligência artificial | F228: INTELIGENCIA_ARTIFICIAL | G228: Artificial Intelligence (AI) | H228: https://coin-images.coingecko.com/coins/images/542/large/Golem_Submark_Positive_RGB.png?1696501761 | I228: https://www.coingecko.com/pt/moedas/golem

Sheet Categorias
A1: name | B1: description | C1: asset_type | D1: segment | E1: Qtd.
A2: ATIVOS_DO_MUNDO_REAL | B2: Ativos do mundo real (RWA) | C2: CRIPTO | D2: Real World Assets (RWA) | E2: =COUNTIFS('Criptos (227)'!$F$2:$F$228,A2,'Criptos (227)'!$G$2:$G$228,D2) -> 5
A3: DEFI | B3: DeFi | C3: CRIPTO | D3: Decentralized Finance (DeFi) | E3: =COUNTIFS('Criptos (227)'!$F$2:$F$228,A3,'Criptos (227)'!$G$2:$G$228,D3) -> 19
A4: GAMES | B4: Games | C4: CRIPTO | D4: Gaming (GameFi) | E4: =COUNTIFS('Criptos (227)'!$F$2:$F$228,A4,'Criptos (227)'!$G$2:$G$228,D4) -> 5
A5: INTELIGENCIA_ARTIFICIAL | B5: Inteligência artificial | C5: CRIPTO | D5: Artificial Intelligence (AI) | E5: =COUNTIFS('Criptos (227)'!$F$2:$F$228,A5,'Criptos (227)'!$G$2:$G$228,D5) -> 14
A6: LAYER_1 | B6: Layer 1 | C6: CRIPTO | D6: Layer 1 (L1) | E6: =COUNTIFS('Criptos (227)'!$F$2:$F$228,A6,'Criptos (227)'!$G$2:$G$228,D6) -> 52
A7: LAYER_2 | B7: Layer 2 | C7: CRIPTO | D7: Layer 2 (L2) | E7: =COUNTIFS('Criptos (227)'!$F$2:$F$228,A7,'Criptos (227)'!$G$2:$G$228,D7) -> 8
A8: MEMECOINS | B8: Memecoins | C8: CRIPTO | D8: Meme | E8: =COUNTIFS('Criptos (227)'!$F$2:$F$228,A8,'Criptos (227)'!$G$2:$G$228,D8) -> 20
A9: METAIS_PRECIOSOS_TOKENIZADOS | B9: Metais preciosos tokenizados | C9: CRIPTO | D9: Tokenized Gold | E9: =COUNTIFS('Criptos (227)'!$F$2:$F$228,A9,'Criptos (227)'!$G$2:$G$228,D9) -> 3
A10: METAIS_PRECIOSOS_TOKENIZADOS | B10: Metais preciosos tokenizados | C10: CRIPTO | D10: Tokenized Silver | E10: =COUNTIFS('Criptos (227)'!$F$2:$F$228,A10,'Criptos (227)'!$G$2:$G$228,D10) -> 1
A11: ORACULOS | B11: Oráculos | C11: CRIPTO | D11: Oracle | E11: =COUNTIFS('Criptos (227)'!$F$2:$F$228,A11,'Criptos (227)'!$G$2:$G$228,D11) -> 2
A12: OUTROS | B12: Outros | C12: CRIPTO | D12: Indefinido | E12: =COUNTIFS('Criptos (227)'!$F$2:$F$228,A12,'Criptos (227)'!$G$2:$G$228,D12) -> 30
A13: PAGAMENTOS | B13: Pagamentos | C13: CRIPTO | D13: Payment Solutions | E13: =COUNTIFS('Criptos (227)'!$F$2:$F$228,A13,'Criptos (227)'!$G$2:$G$228,D13) -> 1
... A16: TOKENS_DE_CORRETORA | B16: Tokens de corretora | C16: CRIPTO | D16: Exchange-based Tokens | E16: =COUNTIFS('Criptos (227)'!$F$2:$F$228,A16,'Criptos (227)'!$G$2:$G$228,D16) -> 30
A17: Total | E17: =SUM(E2:E16) -> 227

Sheet Excluídos (23)
A1: Rank | B1: Ticker (símbolo) | C1: Nome | D1: Id CoinGecko | E1: Motivo | F1: Explicação
A2: 10 | B2: FIGR_HELOC | C2: Figure Heloc | D2: figure-heloc | E2: Fundo/título tokenizado | F2: Cota de fundo ou nota de crédito tokenizada (CLO, fundo monetário, empréstimos). Não é cripto de varejo.
A3: 42 | B3: USYC | C3: Circle USYC | D3: hashnote-usyc | E3: Título público tokenizado | F3: Cota de fundo de títulos do Tesouro americano em blockchain (ex.: BUIDL da BlackRock). É produto de investimento tokenizado, restrito a investidor qualificado, não cripto de varejo.
A4: 44 | B4: BUIDL | C4: BlackRock USD Institutional Digital Liquidity Fund | D4: blackrock-usd-institutional-digital-liquidity-fund | E4: Título público tokenizado | F4: Cota de fundo de títulos do Tesouro americano em blockchain (ex.: BUIDL da BlackRock). É produto de investimento tokenizado, restrito a investidor qualificado, não cripto de varejo.
A5: 45 | B5: USDY | C5: Ondo US Dollar Yield | D5: ondo-us-dollar-yield | E5: Título público tokenizado | F5: Cota de fundo de títulos do Tesouro americano em blockchain (ex.: BUIDL da BlackRock). É produto de investimento tokenizado, restrito a investidor qualificado, não cripto de varejo.
A6: 63 | B6: EURSAFO | C6: Spiko Amundi Overnight Swap Fund (EUR) | D6: spiko-amundi-overnight-swap-fund-eur | E6: Fundo/título tokenizado | F6: Cota de fundo ou nota de crédito tokenizada (CLO, fundo monetário, empréstimos). Não é cripto de varejo.
A7: 71 | B7: BFUSD | C7: BFUSD | D7: bfusd | E7: Stablecoin com rendimento | F7: Versão da stablecoin que acumula rendimento (derivativo). A stablecoin de base, quando está no top 250, entra.
A8: 78 | B8: BCAP | C8: Blockchain Capital | D8: blockchain-capital | E8: Fundo/título tokenizado | F8: Cota de fundo ou nota de crédito tokenizada (CLO, fundo monetário, empréstimos). Não é cripto de varejo.
A9: 89 | B9: EUTBL | C9: Spiko EU T-Bills Money Market Fund | D9: eutbl | E9: Título público tokenizado | F9: Cota de fundo de títulos do Tesouro americano em blockchain (ex.: BUIDL da BlackRock). É produto de investimento tokenizado, restrito a investidor qualificado, não cripto de varejo.
A10: 92 | B10: USTB | C10: Invesco Short Duration US Government Securities Fund | D10: superstate-short-duration-us-government-securities-fund-ustb | E10: Título público tokenizado | F10: Cota de fundo de títulos do Tesouro americano em blockchain (ex.: BUIDL da BlackRock). É produto de investimento tokenizado, restrito a investidor qualificado, não cripto de varejo.
A11: 103 | B11: JAAA | C11: Janus Henderson Anemoy AAA CLO Fund | D11: janus-henderson-anemoy-aaa-clo-fund | E11: Fundo/título tokenizado | F11: Cota de fundo ou nota de crédito tokenizada (CLO, fundo monetário, empréstimos). Não é cripto de varejo.
A12: 110 | B12: 币安人生 | C12: 币安人生 (BinanceLife) | D12: bianrensheng | E12: Símbolo não latino | F12: Símbolo em ideogramas chineses: não serve de ticker no PrimeVest.
A13: 135 | B13: JTRSY | C13: Janus Henderson Anemoy Treasury Fund | D13: janus-henderson-anemoy-treasury-fund | E13: Título público tokenizado | F13: Cota de fundo de títulos do Tesouro americano em blockchain (ex.: BUIDL da BlackRock). É produto de investimento tokenizado, restrito a investidor qualificado, não cripto de varejo.
... A24: 236 | B24: PC0000097 | C24: Tradable LatAm Fintech SSTN | D24: tradable-latam-fintech-sstn | E24: Fundo/título tokenizado | F24: Cota de fundo ou nota de crédito tokenizada (CLO, fundo monetário, empréstimos). Não é cripto de varejo.
