Workbook

Sheet Leia-me
A1: ETFs da B3 — levantamento BRAPI
A3: Fonte | B3: BRAPI (brapi.dev) — /api/v2/tickers?subType=etf e /api/v2/stocks/quote (1 ativo por chamada)
A4: Plano | B4: Gratuito (token do PrimeVest)
A5: Coletado em | B5: 23/09/2026, após o fechamento
A6: Horário da cotação | B6: 23/09/2026 18:31 (Brasília) — regularMarketTime 21:31:30 UTC, igual para todos
A7: Total na BRAPI | B7: 257 marcados como ETF → 219 ETFs de fato + 38 excluídos (aba "Excluídos (38)")
A8: Categorias (decisão de 24/09/2026) | B8: description = tema · name = tema em MAIÚSCULAS sem acento (ex.: RENDA_FIXA_BRASIL) · asset_type = ETF · segment = Miscellaneous ou Indefinido (setor vazio na BRAPI). 12 linhas na aba "Categorias (12)"
A9: Como o tema foi atribuído | B9: Palavras-chave no nome do fundo (ex.: "Tesouro", "IMA-B" → Renda fixa Brasil; "Bitcoin" → Cripto). A BRAPI não informa categoria de ETF
A10: Não informado pela BRAPI | B10: Categoria, valor de mercado (vem nulo), subsetor, dividendos (plano pago)
A12: Resumo por categoria
A13: description | B13: Qtd. de ETFs
A14: Ações Brasil | B14: =COUNTIF('ETFs (219)'!$C$2:$C$220,A14) -> 60
A15: Renda fixa Brasil | B15: =COUNTIF('ETFs (219)'!$C$2:$C$220,A15) -> 59
A16: Ações internacionais | B16: =COUNTIF('ETFs (219)'!$C$2:$C$220,A16) -> 47
A17: Cripto | B17: =COUNTIF('ETFs (219)'!$C$2:$C$220,A17) -> 29
A18: Ouro, prata e commodities | B18: =COUNTIF('ETFs (219)'!$C$2:$C$220,A18) -> 11
A19: Renda fixa internacional | B19: =COUNTIF('ETFs (219)'!$C$2:$C$220,A19) -> 7
A20: Dólar / câmbio | B20: =COUNTIF('ETFs (219)'!$C$2:$C$220,A20) -> 3
A21: FIIs / imobiliário (índice) | B21: =COUNTIF('ETFs (219)'!$C$2:$C$220,A21) -> 2
A22: Outros / estratégia | B22: =COUNTIF('ETFs (219)'!$C$2:$C$220,A22) -> 1
A23: Total | B23: =SUM(B14:B22) -> 219

Sheet ETFs (219)
A1: Ticker | B1: Nome (BRAPI) | C1: Categoria — description | D1: Categoria — name | E1: Categoria — segment | F1: Preço (R$) | G1: Variação (R$) | H1: Variação dia | I1: Abertura (R$) | J1: Mínima dia (R$) | K1: Máxima dia (R$) | L1: Fech. anterior (R$) | M1: Volume (cotas) | N1: Volume financeiro aprox. (R$) | O1: Mín. 52 semanas (R$) | P1: Máx. 52 semanas (R$) | Q1: Posição na faixa 52s | R1: Distância da máx. 52s | S1: Setor (BRAPI) | T1: Logo (URL) | U1: Cotação em
A2: 03BK11 | B2: Galapagos Teva ITBR Tesouro IPCA 3 Anos Fundo de Indice ETF | C2: Renda fixa Brasil | D2: RENDA_FIXA_BRASIL | E2: Miscellaneous | F2: 51.49 | G2: -0.14 | H2: -0.0027 | I2: 51.6 | J2: 51.49 | K2: 51.6 | L2: 51.6 | M2: 2 | N2: =F2*M2 -> 102.98 | O2: 49.97 | P2: 52.75 | Q2: =IF(P2-O2=0,"",(F2-O2)/(P2-O2)) -> 0.54676259 | R2: =IF(P2=0,"",F2/P2-1) -> -0.023886256 | S2: Miscellaneous | T2: https://icons.brapi.dev/icons/03BK11.svg | U2: 46288.772
A3: 10BK11 | B3: Galapagos Teva ITBR Tesouro IPCA 10 Anos Fundo de Indice | C3: Renda fixa Brasil | D3: RENDA_FIXA_BRASIL | E3: Miscellaneous | F3: 52.64 | G3: 0.13 | H3: 0.0025 | I3: 52.64 | J3: 52.64 | K3: 52.64 | L3: 52.64 | M3: 1 | N3: =F3*M3 -> 52.64 | O3: 50.03 | P3: 53.7 | Q3: =IF(P3-O3=0,"",(F3-O3)/(P3-O3)) -> 0.71117166 | R3: =IF(P3=0,"",F3/P3-1) -> -0.019739292 | S3: Miscellaneous | T3: https://icons.brapi.dev/icons/10BK11.svg | U3: 46288.772
A4: 3PRE11 | B4: Galapagos Teva ITBR Tesouro Pre Fixado 3 Anos Fundo de Indice | C4: Renda fixa Brasil | D4: RENDA_FIXA_BRASIL | E4: Miscellaneous | F4: 53.25 | G4: -0.2 | H4: -0.0037 | I4: 53.71 | J4: 53.18 | K4: 53.71 | L4: 53.31 | M4: 75 | N4: =F4*M4 -> 3993.75 | O4: 50.1 | P4: 54.12 | Q4: =IF(P4-O4=0,"",(F4-O4)/(P4-O4)) -> 0.78358209 | R4: =IF(P4=0,"",F4/P4-1) -> -0.016075388 | S4: Miscellaneous | T4: https://icons.brapi.dev/icons/3PRE11.svg | U4: 46288.772
A5: 5PRE11 | B5: IT Now TEVA ITBR Pre 5 Anos Fundo de Indice Responsabilidade Limitada ETF | C5: Renda fixa Brasil | D5: RENDA_FIXA_BRASIL | E5: Miscellaneous | F5: 52.26 | G5: -0.15 | H5: -0.0029 | I5: 52.41 | J5: 52.1 | K5: 52.5 | L5: 52.17 | M5: 16388 | N5: =F5*M5 -> 856436.88 | O5: 48.13 | P5: 52.52 | Q5: =IF(P5-O5=0,"",(F5-O5)/(P5-O5)) -> 0.94077449 | R5: =IF(P5=0,"",F5/P5-1) -> -0.004950495 | S5: Miscellaneous | T5: https://icons.brapi.dev/icons/5PRE11.svg | U5: 46288.772
A6: ABTC11 | B6: BTG Pactual Teva AUVP Bitcoin Fear Arbitrage Fundo de Indice | C6: Cripto | D6: CRIPTO | E6: Miscellaneous | F6: 128.34 | G6: -1.1 | H6: -0.0085 | I6: 131.52 | J6: 127.05 | K6: 135 | L6: 128.45 | M6: 5964 | N6: =F6*M6 -> 765419.76 | O6: 95 | P6: 135 | Q6: =IF(P6-O6=0,"",(F6-O6)/(P6-O6)) -> 0.8335 | R6: =IF(P6=0,"",F6/P6-1) -> -0.049333333 | S6: Miscellaneous | T6: https://icons.brapi.dev/icons/ABTC11.svg | U6: 46288.772
A7: ACWI11 | B7: Trend ETF MSCI ACWI Fundo de Indice | C7: Ações internacionais | D7: ACOES_INTERNACIONAIS | E7: Miscellaneous | F7: 17.39 | G7: 0 | H7: 0 | I7: 17.41 | J7: 17.39 | K7: 17.56 | L7: 17.44 | M7: 187438 | N7: =F7*M7 -> 3259546.8 | O7: 14.76 | P7: 17.94 | Q7: =IF(P7-O7=0,"",(F7-O7)/(P7-O7)) -> 0.82704403 | R7: =IF(P7=0,"",F7/P7-1) -> -0.030657748 | S7: Miscellaneous | T7: https://icons.brapi.dev/icons/ACWI11.svg | U7: 46288.772
A8: AGGX11 | B8: Trend ETF Bloomberg Aggregate US Bonds Classe de Indice - Responsabilidade Limitada | C8: Renda fixa internacional | D8: RENDA_FIXA_INTERNACIONAL | E8: Miscellaneous | F8: 49.4 | G8: 0.12 | H8: 0.0024 | I8: 49.33 | J8: 49.04 | K8: 49.4 | L8: 49.36 | M8: 494 | N8: =F8*M8 -> 24403.6 | O8: 49.04 | P8: 49.95 | Q8: =IF(P8-O8=0,"",(F8-O8)/(P8-O8)) -> 0.3956044 | R8: =IF(P8=0,"",F8/P8-1) -> -0.011011011 | S8: Miscellaneous | T8: https://icons.brapi.dev/icons/AGGX11.svg | U8: 46288.772
A9: AGRI11 | B9: Agri BB ETF Iagro FFS B3 Fundo de Indice ETF | C9: Ações Brasil | D9: ACOES_BRASIL | E9: Miscellaneous | F9: 42 | G9: -0.12 | H9: -0.0028 | I9: 42.52 | J9: 41.92 | K9: 42.52 | L9: 42 | M9: 99 | N9: =F9*M9 -> 4158 | O9: 36.06 | P9: 50.22 | Q9: =IF(P9-O9=0,"",(F9-O9)/(P9-O9)) -> 0.41949153 | R9: =IF(P9=0,"",F9/P9-1) -> -0.16367981 | S9: Miscellaneous | T9: https://icons.brapi.dev/icons/AGRI11.svg | U9: 46288.772
A10: ALUG11 | B10: Investo MSCI US Real Estate ETF | C10: Ações internacionais | D10: ACOES_INTERNACIONAIS | E10: Miscellaneous | F10: 40.68 | G10: -0.21 | H10: -0.0051 | I10: 40.71 | J10: 40.41 | K10: 41.11 | L10: 40.7 | M10: 12865 | N10: =F10*M10 -> 523348.2 | O10: 38.61 | P10: 44.49 | Q10: =IF(P10-O10=0,"",(F10-O10)/(P10-O10)) -> 0.35204082 | R10: =IF(P10=0,"",F10/P10-1) -> -0.085637222 | S10: Miscellaneous | T10: https://icons.brapi.dev/icons/ALUG11.svg | U10: 46288.772
A11: AMAB11 | B11: BTG Pactual Amazonia Para Todos Fundo de Indice | C11: Ações Brasil | D11: ACOES_BRASIL | E11: Indefinido | F11: 10.16 | G11: 0 | H11: 0 | I11: 10.17 | J11: 10.16 | K11: 10.18 | L11: 10.18 | M11: 15 | N11: =F11*M11 -> 152.4 | O11: 9.99 | P11: 10.3 | Q11: =IF(P11-O11=0,"",(F11-O11)/(P11-O11)) -> 0.5483871 | R11: =IF(P11=0,"",F11/P11-1) -> -0.013592233 | S11: (vazio) | T11: https://icons.brapi.dev/icons/AMAB11.svg | U11: 46288.772
A12: AREA11 | B12: BTG Pactual Teva ITBR IPCA Rendimento Fundo de Indice | C12: Renda fixa Brasil | D12: RENDA_FIXA_BRASIL | E12: Miscellaneous | F12: 106.07 | G12: -0.03 | H12: -0.0003 | I12: 106.4 | J12: 105.88 | K12: 106.41 | L12: 106.3 | M12: 3061 | N12: =F12*M12 -> 324680.27 | O12: 99.33 | P12: 107.96 | Q12: =IF(P12-O12=0,"",(F12-O12)/(P12-O12)) -> 0.78099652 | R12: =IF(P12=0,"",F12/P12-1) -> -0.017506484 | S12: Miscellaneous | T12: https://icons.brapi.dev/icons/AREA11.svg | U12: 46288.772
A13: ARGE11 | B13: Investo Argentina Fundo de Indice | C13: Ações internacionais | D13: ACOES_INTERNACIONAIS | E13: Miscellaneous | F13: 12.6 | G13: 0.01 | H13: 0.0008 | I13: 12.76 | J13: 12.6 | K13: 12.86 | L13: 12.67 | M13: 938 | N13: =F13*M13 -> 11818.8 | O13: 7.55 | P13: 14.7 | Q13: =IF(P13-O13=0,"",(F13-O13)/(P13-O13)) -> 0.70629371 | R13: =IF(P13=0,"",F13/P13-1) -> -0.14285714 | S13: Miscellaneous | T13: https://icons.brapi.dev/icons/ARGE11.svg | U13: 46288.772
... A220: XSPI11 | B220: BUENA VISTA DEX VETTAFI NEOS BOOSTED S&P 500 HIGH INCOME FUNDO DE INDICE DE RESPONSABILIDADE LIMITAD | C220: Ações internacionais | D220: ACOES_INTERNACIONAIS | E220: Miscellaneous | F220: 107.42 | G220: -0.02 | H220: -0.0002 | I220: 107.82 | J220: 107.29 | K220: 107.94 | L220: 107.42 | M220: 806 | N220: =F220*M220 -> 86580.52 | O220: 99.05 | P220: 111.2 | Q220: =IF(P220-O220=0,"",(F220-O220)/(P220-O220)) -> 0.68888889 | R220: =IF(P220=0,"",F220/P220-1) -> -0.033992806 | S220: Miscellaneous | T220: https://icons.brapi.dev/icons/XSPI11.svg | U220: 46288.772

Sheet Categorias (12)
A1: name | B1: description | C1: asset_type | D1: segment | E1: Qtd. de ETFs
A2: ACOES_BRASIL | B2: Ações Brasil | C2: ETF | D2: Indefinido | E2: =COUNTIFS('ETFs (219)'!$D$2:$D$220,A2,'ETFs (219)'!$E$2:$E$220,D2) -> 1
A3: ACOES_BRASIL | B3: Ações Brasil | C3: ETF | D3: Miscellaneous | E3: =COUNTIFS('ETFs (219)'!$D$2:$D$220,A3,'ETFs (219)'!$E$2:$E$220,D3) -> 59
A4: ACOES_INTERNACIONAIS | B4: Ações internacionais | C4: ETF | D4: Miscellaneous | E4: =COUNTIFS('ETFs (219)'!$D$2:$D$220,A4,'ETFs (219)'!$E$2:$E$220,D4) -> 47
A5: CRIPTO | B5: Cripto | C5: ETF | D5: Indefinido | E5: =COUNTIFS('ETFs (219)'!$D$2:$D$220,A5,'ETFs (219)'!$E$2:$E$220,D5) -> 1
A6: CRIPTO | B6: Cripto | C6: ETF | D6: Miscellaneous | E6: =COUNTIFS('ETFs (219)'!$D$2:$D$220,A6,'ETFs (219)'!$E$2:$E$220,D6) -> 28
A7: DOLAR_CAMBIO | B7: Dólar / câmbio | C7: ETF | D7: Miscellaneous | E7: =COUNTIFS('ETFs (219)'!$D$2:$D$220,A7,'ETFs (219)'!$E$2:$E$220,D7) -> 3
A8: FIIS_IMOBILIARIO | B8: FIIs / imobiliário (índice) | C8: ETF | D8: Miscellaneous | E8: =COUNTIFS('ETFs (219)'!$D$2:$D$220,A8,'ETFs (219)'!$E$2:$E$220,D8) -> 2
A9: OURO_PRATA_COMMODITIES | B9: Ouro, prata e commodities | C9: ETF | D9: Miscellaneous | E9: =COUNTIFS('ETFs (219)'!$D$2:$D$220,A9,'ETFs (219)'!$E$2:$E$220,D9) -> 11
A10: OUTROS_ESTRATEGIA | B10: Outros / estratégia | C10: ETF | D10: Indefinido | E10: =COUNTIFS('ETFs (219)'!$D$2:$D$220,A10,'ETFs (219)'!$E$2:$E$220,D10) -> 1
A11: RENDA_FIXA_BRASIL | B11: Renda fixa Brasil | C11: ETF | D11: Indefinido | E11: =COUNTIFS('ETFs (219)'!$D$2:$D$220,A11,'ETFs (219)'!$E$2:$E$220,D11) -> 2
A12: RENDA_FIXA_BRASIL | B12: Renda fixa Brasil | C12: ETF | D12: Miscellaneous | E12: =COUNTIFS('ETFs (219)'!$D$2:$D$220,A12,'ETFs (219)'!$E$2:$E$220,D12) -> 57
A13: RENDA_FIXA_INTERNACIONAL | B13: Renda fixa internacional | C13: ETF | D13: Miscellaneous | E13: =COUNTIFS('ETFs (219)'!$D$2:$D$220,A13,'ETFs (219)'!$E$2:$E$220,D13) -> 7
A14: Total | E14: =SUM(E2:E13) -> 219

Sheet Excluídos (38)
A1: Ticker | B1: Nome (BRAPI) | C1: Último preço (R$) | D1: Motivo | E1: Explicação
A2: BBSD | B2: BB ETF S&P Dividendos Brasil Fundo de Indice | C2: 135.1 | D2: Sem sufixo 11 | E2: Duplicata do mesmo fundo com sufixo 11 (ex.: BOVA × BOVA11). O ticker negociado é o com 11.
A3: BOVA | B3: iShares Ibovespa Fundo de Indice | C3: 182.93 | D3: Sem sufixo 11 | E3: Duplicata do mesmo fundo com sufixo 11 (ex.: BOVA × BOVA11). O ticker negociado é o com 11.
A4: BOVV | B4: IT Now Ibovespa Fundo de Indice Cotas | C4: 191.93 | D4: Sem sufixo 11 | E4: Duplicata do mesmo fundo com sufixo 11 (ex.: BOVA × BOVA11). O ticker negociado é o com 11.
A5: DIVO | B5: IT NOW IDIV Fundo de Indice Cotas | C5: 131.71 | D5: Sem sufixo 11 | E5: Duplicata do mesmo fundo com sufixo 11 (ex.: BOVA × BOVA11). O ticker negociado é o com 11.
A6: ECOO | B6: iShares Indice Carbono Eficiente (ICO2) Brasil Fundo de Indice | C6: 154.97 | D6: Sem sufixo 11 | E6: Duplicata do mesmo fundo com sufixo 11 (ex.: BOVA × BOVA11). O ticker negociado é o com 11.
A7: FIND | B7: IT Now IFNC Fundo de Indice | C7: 190.95 | D7: Sem sufixo 11 | E7: Duplicata do mesmo fundo com sufixo 11 (ex.: BOVA × BOVA11). O ticker negociado é o com 11.
A8: GOVE | B8: IT Now IGCT Fundo De Indice | C8: 80.57 | D8: Sem sufixo 11 | E8: Duplicata do mesmo fundo com sufixo 11 (ex.: BOVA × BOVA11). O ticker negociado é o com 11.
A9: ISUS | B9: IT Now ISE Fundo de Indice | C9: 44.88 | D9: Sem sufixo 11 | E9: Duplicata do mesmo fundo com sufixo 11 (ex.: BOVA × BOVA11). O ticker negociado é o com 11.
A10: SCVB | B10: INVESTO MARKETVECTOR BRAZIL SMALL CAP VALUE ETF | C10: 83.47 | D10: Sem sufixo 11 | E10: Duplicata do mesmo fundo com sufixo 11 (ex.: BOVA × BOVA11). O ticker negociado é o com 11.
A11: XBOV | B11: Caixa ETF Ibovespa Fundo Indice Cotas | C11: 180.97 | D11: Sem sufixo 11 | E11: Duplicata do mesmo fundo com sufixo 11 (ex.: BOVA × BOVA11). O ticker negociado é o com 11.
A12: BDIF11 | B12: BTG Pactual Divida Infra FI em Cotas de Fundos Incentivados de Investimento em Infra Rend Fix Cred Priv | C12: 69.48 | D12: FI-Infra | E12: Fundo de debêntures incentivadas (FI-Infra/FIC). A BRAPI marca como ETF, mas não é fundo de índice.
A13: BIDB11 | B13: Inter Infra Fundo de Investimento em Cotas de Fundos Incentivados de Investimento em Infraestrutura Ren Fix Cred Priv | C13: 75.58 | D13: FI-Infra | E13: Fundo de debêntures incentivadas (FI-Infra/FIC). A BRAPI marca como ETF, mas não é fundo de índice.
... A39: PSVM11 | B39: Porto Sudeste VM SA | C39: 15.88 | D39: Não é ETF | E39: Não é ETF: fundo fiscal antigo (FINAM/FINOR/FISET), empresa (Porto Sudeste) ou fundo imobiliário/agro.
